Workbook
Name OLE_LINK1: Pivot!$E$17
Name Slicer_Delivery_Status: #N/A
Name Slicer_Month: #N/A
Name Slicer_Payment_Method: #N/A
Name Slicer_Region: #N/A

Sheet Pivot
A2: 2. Show Total Sales Amount by Region and Product Category
A3: Region | B3: Product Category | C3: Sum of Sales Amount
A4: Central | B4: Books | C4: 84
B5: Electronics | C5: 2662 | E5: 2. Count of Orders by Delivery Status
B6: Fashion | C6: 210 | E6: Delivery Status | F6: Count of Order ID
B7: Home | C7: 2063 | E7: Cancelled | F7: 30
B8: Toys | C8: 437 | E8: Delivered | F8: 34
A9: Central Total | C9: 5456 | E9: In Transit | F9: 36
A10: East | B10: Books | C10: 394 | E10: Grand Total | F10: 100
B11: Electronics | C11: 365
B12: Fashion | C12: 711 | E12: 2. Average Delivery Time = Delivery Date – Order Date
B13: Home | C13: 741 | E13: Average of Time in delivery(Days)
B14: Toys | C14: 1424 | E14: 12.323529
A15: East Total | C15: 3635
A16: North | B16: Books | C16: 464
B17: Electronics | C17: 6522 | E17: 2. Add filter for Payment Method and Product Category
B18: Fashion | C18: 788 | E18: Product Category | F18: (All)
B19: Home | C19: 2131 | E19: Payment Method | F19: (All)
B20: Toys | C20: 586
A21: North Total | C21: 10491
A22: South | B22: Books | C22: 423
B23: Electronics | C23: 3938
B24: Fashion | C24: 1032
B25: Home | C25: 1881
B26: Toys | C26: 43
A27: South Total | C27: 7317
A28: West | B28: Books | C28: 350
B29: Electronics | C29: 1722
B30: Fashion | C30: 1131
B31: Home | C31: 4135
B32: Toys | C32: 1021
A33: West Total | C33: 8359
A34: Grand Total | C34: 35258
F36: KPI Cards
F38: 4. Total Revenue
A39: 4. Create a field: Cancellation Rate by Region (Cancelled Orders / Total Orders) | F39: Sum of Sales Amount
A40: Region | B40: Sum of Cancelled Flag | C40: Count of Order ID | F40: 35258
A41: Central | B41: 5 | C41: 14
A42: East | B42: 3 | C42: 18 | F42: 4. % of Fast Deliveries
A43: North | B43: 10 | C43: 25 | F43: Order status | G43: (All)
A44: South | B44: 4 | C44: 20
A45: West | B45: 8 | C45: 23 | F45: Delivery Performance | G45: Count of Order ID
A46: Grand Total | B46: 30 | C46: 100 | F46: Fast | G46: 0.77
F47: Slow | G47: 0.23
F48: Grand Total | G48: 1
F50: 4. Top 3 Performing Regions
F51: Region | G51: Sum of Sales Amount | H51: =$F$52&CHAR(10)&$F$53&CHAR(10)&$F$54 -> North West South
A52: 4. Add Calculated Field in Pivot: Effective Sales = Sales Amount for Delivered Orders only | F52: North | G52: 10491
A53: Sum of Effective Sales Amount | F53: West | G53: 8359
A54: 35258 | F54: South | G54: 7317
F55: Central | G55: 5456
F56: East | G56: 3635
F57: Product Name | G57: Sum of Sales Amount
F58: Smartphone | G58: 9644
F59: Grand Total | G59: 9644
A69: 5. Use Pivot Charts and Slicers to allow filtering by Region, Payment Method, and Delivery Status
A70: Region | B70: Sum of Sales Amount
A71: Central | B71: 5456
A72: East | B72: 3635
A73: North | B73: 10491
A74: South | B74: 7317
A75: West | B75: 8359
A76: Grand Total | B76: 35258
A79: 5. Highlight high-performing regions or products using Conditional Formatting
A80: Product Name | B80: Sum of Sales Amount
A81: Action Figure | B81: 669
A82: Backpack | B82: 518
A83: Bluetooth Speaker | B83: 731
A84: Cookware Set | B84: 2496 | D84: 5. Add a drop-down to filter sales by Month (group Order Date in Pivot)
A85: Cookware Set Pro | B85: 5151 | D85: Order Date | E85: (All)
A86: Doll House | B86: 1530
A87: Formal Shirt | B87: 995 | D87: Sum of Sales Amount
A88: Gaming Mouse | B88: 1392 | D88: 35258
A89: Headphones | B89: 1212
A90: Jeans | B90: 581
A91: Lamp | B91: 320
A92: Leg Set | B92: 1124
A93: Magazine | B93: 165 | D93: DELIVERY PERFORMANCE BY ORDER ID
A94: Novel | B94: 232 | D94: Time in delivery(Days) | E94: (All)
A95: Puzzle | B95: 188
A96: Shoes | B96: 1239 | D96: Delivery Performance | E96: Count of Order ID
A97: Smartphone | B97: 9644 | D97: Fast | E97: 77
A98: Smartwatch | B98: 2230 | D98: Slow | E98: 23
A99: Textbook | B99: 1318 | D99: Grand Total | E99: 100
A100: T-Shirt | B100: 539
A101: Vacuum Cleaner | B101: 2144
A102: Wall Clock | B102: 840
A103: Grand Total | B103: 35258

Sheet DashBoard

Sheet Insights
A2: Key Insights
A4: 1. Total Revenue: 35,258
A5: 2. Top Performing Region: North (10,491)
A6: 3. Highest Selling Product: Smartphone
A7: 4. Fast Deliveries: 77% of Orders
A8: 5. Top Regions: North & West
A9: 6. Interactive Filters: | C9: 1 | D9: Region
C10: 2 | D10: Delivery Status
C11: 3 | D11: Payment Method
C12: 4 | D12: Month

Sheet QA
A1: 1. What is the most successful product category in terms of revenue?
A2: >>Electronics is the most successful product category, generating the highest revenue compared to other categories
A4: 2. Which region has the highest order cancellation rate?
A5: >>The North region has the highest cancellation rate, indicating potential delivery or supply issues.
A7: 3. How many orders were delivered within 2 days?
A8: >>7 deliveres are delivered within 2 days.
A10: 4. How has the use of XLOOKUP simplified cross-sheet analysis?
A11: >>XLOOKUP simplified cross-sheet analysis by replacing complex VLOOKUP formulas.
A12: It allows dynamic lookups in any direction, eliminates column index errors, and provides built-in error handling,
A13: making data reconciliation faster and more reliable.
A15: 5. What recommendations would you give to improve delivery performance?
A16: >>Overall, the dashboard highlights key revenue drivers and delivery bottlenecks, enabling data-driven decisions to improve customer satisfaction and operational efficiency.

Sheet AmozonSales
A1: Order ID | B1: Order Date | C1: Month | D1: Year | E1: Delivery Date | F1: Cancel Date | G1: Customer ID | H1: Product ID | I1: Region | J1: Sale Price/Unit | K1: Quantity | L1: Total Amount | M1: Payment Method | N1: Delivery Status | O1: Fulfillment Partner | P1: Sales Amount | Q1: Time in delivery(Days) | R1: Product Category | S1: Customer Name | T1: Delivery Performance | U1: Date of Delivery | V1: Order status | W1: Cancelled Flag | X1: Product Name
A2: ORD0001 | B2: 45291 | C2: =TEXT(B2,"mmm") -> Dec | D2: =TEXT(B2,"yyy") -> 2023 | F2: 45323 | G2: CUST021 | H2: PROD012 | I2: North | J2: 44 | K2: 1 | L2: 44 | M2: Apple Pay | N2: Cancelled | O2: DHL | P2: =K2*J2 -> 44 | Q2: =IF(N2="Delivered",E2-B2,"") | R2: {=_xlfn.XLOOKUP(Table1[[#This Row],[Product ID]],Table2[[#All],[Product ID]],Table2[[#All],[Category]])} -> Home | S2: {=_xlfn.XLOOKUP(Table1[[#This Row],[Customer ID]],Table4[[#All],[Customer ID]],Table4[[#All],[Customer Name]])} -> Zoe Mitchell | T2: =IF(E2-B2<=2,"Fast","Slow") -> Fast | U2: =IFERROR(IF(E2="","Cancellations",E2),0) -> Cancellations | V2: =IF(OR(F2<>"",N2="Cancelled"),"Cancelled","Delivered") -> Cancelled | W2: =IF(V2="Cancelled",1,0) -> 1 | X2: =VLOOKUP(H2,ProductMaster!$A$1:$E$23,2,0) -> Lamp
A3: ORD0002 | B3: 44979 | C3: =TEXT(B3,"mmm") -> Feb | D3: =TEXT(B3,"yyy") -> 2023 | E3: 44981 | G3: CUST029 | H3: PROD018 | I3: East | J3: 96 | K3: 4 | L3: 384 | M3: Credit Card | N3: Delivered | O3: DHL | P3: =K3*J3 -> 384 | Q3: =IF(N3="Delivered",E3-B3,"") -> 2 | R3: {=_xlfn.XLOOKUP(Table1[[#This Row],[Product ID]],Table2[[#All],[Product ID]],Table2[[#All],[Category]])} -> Toys | S3: {=_xlfn.XLOOKUP(Table1[[#This Row],[Customer ID]],Table4[[#All],[Customer ID]],Table4[[#All],[Customer Name]])} -> Ava White | T3: =IF(E3-B3<=2,"Fast","Slow") -> Fast | U3: =IFERROR(IF(E3="","Cancellations",E3),0) -> 44981 | V3: =IF(OR(F3<>"",N3="Cancelled"),"Cancelled","Delivered") -> Delivered | W3: =IF(V3="Cancelled",1,0) -> 0 | X3: =VLOOKUP(H3,ProductMaster!$A$1:$E$23,2,0) -> Doll House
A4: ORD0003 | B4: 45240 | C4: =TEXT(B4,"mmm") -> Nov | D4: =TEXT(B4,"yyy") -> 2023 | G4: CUST021 | H4: PROD013 | I4: South | J4: 194 | K4: 4 | L4: 776 | M4: Credit Card | N4: In Transit | O4: USPS | P4: =K4*J4 -> 776 | Q4: =IF(N4="Delivered",E4-B4,"") | R4: {=_xlfn.XLOOKUP(Table1[[#This Row],[Product ID]],Table2[[#All],[Product ID]],Table2[[#All],[Category]])} -> Home | S4: {=_xlfn.XLOOKUP(Table1[[#This Row],[Customer ID]],Table4[[#All],[Customer ID]],Table4[[#All],[Customer Name]])} -> Zoe Mitchell | T4: =IF(E4-B4<=2,"Fast","Slow") -> Fast | U4: =IFERROR(IF(E4="","Cancellations",E4),0) -> Cancellations | V4: =IF(OR(F4<>"",N4="Cancelled"),"Cancelled","Delivered") -> Delivered | W4: =IF(V4="Cancelled",1,0) -> 0 | X4: =VLOOKUP(H4,ProductMaster!$A$1:$E$23,2,0) -> Vacuum Cleaner
A5: ORD0004 | B5: 45051 | C5: =TEXT(B5,"mmm") -> May | D5: =TEXT(B5,"yyy") -> 2023 | F5: 45235 | G5: CUST044 | H5: PROD013 | I5: North | J5: 196 | K5: 3 | L5: 588 | M5: PayPal | N5: Cancelled | O5: UPS | P5: =K5*J5 -> 588 | Q5: =IF(N5="Delivered",E5-B5,"") | R5: {=_xlfn.XLOOKUP(Table1[[#This Row],[Product ID]],Table2[[#All],[Product ID]],Table2[[#All],[Category]])} -> Home | S5: {=_xlfn.XLOOKUP(Table1[[#This Row],[Customer ID]],Table4[[#All],[Customer ID]],Table4[[#All],[Customer Name]])} -> Grace Ward | T5: =IF(E5-B5<=2,"Fast","Slow") -> Fast | U5: =IFERROR(IF(E5="","Cancellations",E5),0) -> Cancellations | V5: =IF(OR(F5<>"",N5="Cancelled"),"Cancelled","Delivered") -> Cancelled | W5: =IF(V5="Cancelled",1,0) -> 1 | X5: =VLOOKUP(H5,ProductMaster!$A$1:$E$23,2,0) -> Vacuum Cleaner
A6: ORD0005 | B6: 44959 | C6: =TEXT(B6,"mmm") -> Feb | D6: =TEXT(B6,"yyy") -> 2023 | E6: 45048 | G6: CUST027 | H6: PROD010 | I6: North | J6: 59 | K6: 1 | L6: 59 | M6: PayPal | N6: Delivered | O6: Amazon Logistics | P6: =K6*J6 -> 59 | Q6: =IF(N6="Delivered",E6-B6,"") -> 89 | R6: {=_xlfn.XLOOKUP(Table1[[#This Row],[Product ID]],Table2[[#All],[Product ID]],Table2[[#All],[Category]])} -> Fashion | S6: {=_xlfn.XLOOKUP(Table1[[#This Row],[Customer ID]],Table4[[#All],[Customer ID]],Table4[[#All],[Customer Name]])} -> Hazel Brooks | T6: =IF(E6-B6<=2,"Fast","Slow") -> Slow | U6: =IFERROR(IF(E6="","Cancellations",E6),0) -> 45048 | V6: =IF(OR(F6<>"",N6="Cancelled"),"Cancelled","Delivered") -> Delivered | W6: =IF(V6="Cancelled",1,0) -> 0 | X6: =VLOOKUP(H6,ProductMaster!$A$1:$E$23,2,0) -> Jeans
A7: ORD0006 | B7: 44937 | C7: =TEXT(B7,"mmm") -> Jan | D7: =TEXT(B7,"yyy") -> 2023 | F7: 44968 | G7: CUST009 | H7: PROD010 | I7: North | J7: 58 | K7: 4 | L7: 232 | M7: Amazon Pay | N7: Cancelled | O7: DHL | P7: =K7*J7 -> 232 | Q7: =IF(N7="Delivered",E7-B7,"") | R7: {=_xlfn.XLOOKUP(Table1[[#This Row],[Product ID]],Table2[[#All],[Product ID]],Table2[[#All],[Category]])} -> Fashion | S7: {=_xlfn.XLOOKUP(Table1[[#This Row],[Customer ID]],Table4[[#All],[Customer ID]],Table4[[#All],[Customer Name]])} -> Jackson Allen | T7: =IF(E7-B7<=2,"Fast","Slow") -> Fast | U7: =IFERROR(IF(E7="","Cancellations",E7),0) -> Cancellations | V7: =IF(OR(F7<>"",N7="Cancelled"),"Cancelled","Delivered") -> Cancelled | W7: =IF(V7="Cancelled",1,0) -> 1 | X7: =VLOOKUP(H7,ProductMaster!$A$1:$E$23,2,0) -> Jeans
A8: ORD0007 | B8: 45152 | C8: =TEXT(B8,"mmm") -> Aug | D8: =TEXT(B8,"yyy") -> 2023 | F8: 45156 | G8: CUST042 | H8: PROD020 | I8: Central | J8: 105 | K8: 3 | L8: 315 | M8: Debit Card | N8: Cancelled | O8: DHL | P8: =K8*J8 -> 315 | Q8: =IF(N8="Delivered",E8-B8,"") | R8: {=_xlfn.XLOOKUP(Table1[[#This Row],[Product ID]],Table2[[#All],[Product ID]],Table2[[#All],[Category]])} -> Electronics | S8: {=_xlfn.XLOOKUP(Table1[[#This Row],[Customer ID]],Table4[[#All],[Customer ID]],Table4[[#All],[Customer Name]])} -> Noah Wilson | T8: =IF(E8-B8<=2,"Fast","Slow") -> Fast | U8: =IFERROR(IF(E8="","Cancellations",E8),0) -> Cancellations | V8: =IF(OR(F8<>"",N8="Cancelled"),"Cancelled","Delivered") -> Cancelled | W8: =IF(V8="Cancelled",1,0) -> 1 | X8: =VLOOKUP(H8,ProductMaster!$A$1:$E$23,2,0) -> Bluetooth Speaker
A9: ORD0008 | B9: 44930 | C9: =TEXT(B9,"mmm") -> Jan | D9: =TEXT(B9,"yyy") -> 2023 | F9: 45081 | G9: CUST019 | H9: PROD021 | I9: West | J9: 37 | K9: 5 | L9: 185 | M9: PayPal | N9: Cancelled | O9: DHL | P9: =K9*J9 -> 185 | Q9: =IF(N9="Delivered",E9-B9,"") | R9: {=_xlfn.XLOOKUP(Table1[[#This Row],[Product ID]],Table2[[#All],[Product ID]],Table2[[#All],[Category]])} -> Home | S9: {=_xlfn.XLOOKUP(Table1[[#This Row],[Customer ID]],Table4[[#All],[Customer ID]],Table4[[#All],[Customer Name]])} -> Ava Robinson | T9: =IF(E9-B9<=2,"Fast","Slow") -> Fast | U9: =IFERROR(IF(E9="","Cancellations",E9),0) -> Cancellations | V9: =IF(OR(F9<>"",N9="Cancelled"),"Cancelled","Delivered") -> Cancelled | W9: =IF(V9="Cancelled",1,0) -> 1 | X9: =VLOOKUP(H9,ProductMaster!$A$1:$E$23,2,0) -> Wall Clock
A10: ORD0009 | B10: 45128 | C10: =TEXT(B10,"mmm") -> Jul | D10: =TEXT(B10,"yyy") -> 2023 | G10: CUST013 | H10: PROD019 | I10: Central | J10: 44 | K10: 2 | L10: 88 | M10: Credit Card | N10: In Transit | O10: Amazon Logistics | P10: =K10*J10 -> 88 | Q10: =IF(N10="Delivered",E10-B10,"") | R10: {=_xlfn.XLOOKUP(Table1[[#This Row],[Product ID]],Table2[[#All],[Product ID]],Table2[[#All],[Category]])} -> Fashion | S10: {=_xlfn.XLOOKUP(Table1[[#This Row],[Customer ID]],Table4[[#All],[Customer ID]],Table4[[#All],[Customer Name]])} -> Olivia Martinez | T10: =IF(E10-B10<=2,"Fast","Slow") -> Fast | U10: =IFERROR(IF(E10="","Cancellations",E10),0) -> Cancellations | V10: =IF(OR(F10<>"",N10="Cancelled"),"Cancelled","Delivered") -> Delivered | W10: =IF(V10="Cancelled",1,0) -> 0 | X10: =VLOOKUP(H10,ProductMaster!$A$1:$E$23,2,0) -> Formal Shirt
A11: ORD0010 | B11: 45289 | C11: =TEXT(B11,"mmm") -> Dec | D11: =TEXT(B11,"yyy") -> 2023 | G11: CUST019 | H11: PROD003 | I11: South | J11: 141 | K11: 4 | L11: 564 | M11: Debit Card | N11: In Transit | O11: DHL | P11: =K11*J11 -> 564 | Q11: =IF(N11="Delivered",E11-B11,"") | R11: {=_xlfn.XLOOKUP(Table1[[#This Row],[Product ID]],Table2[[#All],[Product ID]],Table2[[#All],[Category]])} -> Home | S11: {=_xlfn.XLOOKUP(Table1[[#This Row],[Customer ID]],Table4[[#All],[Customer ID]],Table4[[#All],[Customer Name]])} -> Ava Robinson | T11: =IF(E11-B11<=2,"Fast","Slow") -> Fast | U11: =IFERROR(IF(E11="","Cancellations",E11),0) -> Cancellations | V11: =IF(OR(F11<>"",N11="Cancelled"),"Cancelled","Delivered") -> Delivered | W11: =IF(V11="Cancelled",1,0) -> 0 | X11: =VLOOKUP(H11,ProductMaster!$A$1:$E$23,2,0) -> Cookware Set
A12: ORD0011 | B12: 45021 | C12: =TEXT(B12,"mmm") -> Apr | D12: =TEXT(B12,"yyy") -> 2023 | F12: 45143 | G12: CUST046 | H12: PROD014 | I12: South | J12: 249 | K12: 1 | L12: 249 | M12: Amazon Pay | N12: Cancelled | O12: USPS | P12: =K12*J12 -> 249 | Q12: =IF(N12="Delivered",E12-B12,"") | R12: {=_xlfn.XLOOKUP(Table1[[#This Row],[Product ID]],Table2[[#All],[Product ID]],Table2[[#All],[Category]])} -> Electronics | S12: {=_xlfn.XLOOKUP(Table1[[#This Row],[Customer ID]],Table4[[#All],[Customer ID]],Table4[[#All],[Customer Name]])} -> Emily Johnson | T12: =IF(E12-B12<=2,"Fast","Slow") -> Fast | U12: =IFERROR(IF(E12="","Cancellations",E12),0) -> Cancellations | V12: =IF(OR(F12<>"",N12="Cancelled"),"Cancelled","Delivered") -> Cancelled | W12: =IF(V12="Cancelled",1,0) -> 1 | X12: =VLOOKUP(H12,ProductMaster!$A$1:$E$23,2,0) -> Smartwatch
A13: ORD0012 | B13: 45132 | C13: =TEXT(B13,"mmm") -> Jul | D13: =TEXT(B13,"yyy") -> 2023 | G13: CUST045 | H13: PROD014 | I13: Central | J13: 247 | K13: 3 | L13: 741 | M13: Amazon Pay | N13: In Transit | O13: FedEx | P13: =K13*J13 -> 741 | Q13: =IF(N13="Delivered",E13-B13,"") | R13: {=_xlfn.XLOOKUP(Table1[[#This Row],[Product ID]],Table2[[#All],[Product ID]],Table2[[#All],[Category]])} -> Electronics | S13: {=_xlfn.XLOOKUP(Table1[[#This Row],[Customer ID]],Table4[[#All],[Customer ID]],Table4[[#All],[Customer Name]])} -> Emily Johnson | T13: =IF(E13-B13<=2,"Fast","Slow") -> Fast | U13: =IFERROR(IF(E13="","Cancellations",E13),0) -> Cancellations | V13: =IF(OR(F13<>"",N13="Cancelled"),"Cancelled","Delivered") -> Delivered | W13: =IF(V13="Cancelled",1,0) -> 0 | X13: =VLOOKUP(H13,ProductMaster!$A$1:$E$23,2,0) -> Smartwatch
A14: ORD0013 | B14: 44982 | C14: =TEXT(B14,"mmm") -> Feb | D14: =TEXT(B14,"yyy") -> 2023 | F14: 44985 | G14: CUST023 | H14: PROD006 | I14: Central | J14: 96 | K14: 1 | L14: 96 | M14: Apple Pay | N14: Cancelled | O14: Amazon Logistics | P14: =K14*J14 -> 96 | Q14: =IF(N14="Delivered",E14-B14,"") | R14: {=_xlfn.XLOOKUP(Table1[[#This Row],[Product ID]],Table2[[#All],[Product ID]],Table2[[#All],[Category]])} -> Fashion | S14: {=_xlfn.XLOOKUP(Table1[[#This Row],[Customer ID]],Table4[[#All],[Customer ID]],Table4[[#All],[Customer Name]])} -> Charlotte Reed | T14: =IF(E14-B14<=2,"Fast","Slow") -> Fast | U14: =IFERROR(IF(E14="","Cancellations",E14),0) -> Cancellations | V14: =IF(OR(F14<>"",N14="Cancelled"),"Cancelled","Delivered") -> Cancelled | W14: =IF(V14="Cancelled",1,0) -> 1 | X14: =VLOOKUP(H14,ProductMaster!$A$1:$E$23,2,0) -> Shoes
A15: ORD0014 | B15: 44981 | C15: =TEXT(B15,"mmm") -> Feb | D15: =TEXT(B15,"yyy") -> 2023 | F15: 44982 | G15: CUST033 | H15: PROD017 | I15: West | J15: 74 | K15: 5 | L15: 370 | M15: Apple Pay | N15: Cancelled | O15: Amazon Logistics | P15: =K15*J15 -> 370 | Q15: =IF(N15="Delivered",E15-B15,"") | R15: {=_xlfn.XLOOKUP(Table1[[#This Row],[Product ID]],Table2[[#All],[Product ID]],Table2[[#All],[Category]])} -> Electronics | S15: {=_xlfn.XLOOKUP(Table1[[#This Row],[Customer ID]],Table4[[#All],[Customer ID]],Table4[[#All],[Customer Name]])} -> Hazel Rivera | T15: =IF(E15-B15<=2,"Fast","Slow") -> Fast | U15: =IFERROR(IF(E15="","Cancellations",E15),0) -> Cancellations | V15: =IF(OR(F15<>"",N15="Cancelled"),"Cancelled","Delivered") -> Cancelled | W15: =IF(V15="Cancelled",1,0) -> 1 | X15: =VLOOKUP(H15,ProductMaster!$A$1:$E$23,2,0) -> Gaming Mouse
A16: ORD0015 | B16: 45164 | C16: =TEXT(B16,"mmm") -> Aug | D16: =TEXT(B16,"yyy") -> 2023 | F16: 44966 | G16: CUST033 | H16: PROD005 | I16: South | J16: 27 | K16: 1 | L16: 27 | M16: Credit Card | N16: Cancelled | O16: Amazon Logistics | P16: =K16*J16 -> 27 | Q16: =IF(N16="Delivered",E16-B16,"") | R16: {=_xlfn.XLOOKUP(Table1[[#This Row],[Product ID]],Table2[[#All],[Product ID]],Table2[[#All],[Category]])} -> Fashion | S16: {=_xlfn.XLOOKUP(Table1[[#This Row],[Customer ID]],Table4[[#All],[Customer ID]],Table4[[#All],[Customer Name]])} -> Hazel Rivera | T16: =IF(E16-B16<=2,"Fast","Slow") -> Fast | U16: =IFERROR(IF(E16="","Cancellations",E16),0) -> Cancellations | V16: =IF(OR(F16<>"",N16="Cancelled"),"Cancelled","Delivered") -> Cancelled | W16: =IF(V16="Cancelled",1,0) -> 1 | X16: =VLOOKUP(H16,ProductMaster!$A$1:$E$23,2,0) -> T-Shirt
A17: ORD0016 | B17: 44970 | C17: =TEXT(B17,"mmm") -> Feb | D17: =TEXT(B17,"yyy") -> 2023 | G17: CUST047 | H17: PROD005 | I17: South | J17: 27 | K17: 3 | L17: 81 | M17: Debit Card | N17: In Transit | O17: Amazon Logistics | P17: =K17*J17 -> 81 | Q17: =IF(N17="Delivered",E17-B17,"") | R17: {=_xlfn.XLOOKUP(Table1[[#This Row],[Product ID]],Table2[[#All],[Product ID]],Table2[[#All],[Category]])} -> Fashion | S17: {=_xlfn.XLOOKUP(Table1[[#This Row],[Customer ID]],Table4[[#All],[Customer ID]],Table4[[#All],[Customer Name]])} -> Scarlett Murphy | T17: =IF(E17-B17<=2,"Fast","Slow") -> Fast | U17: =IFERROR(IF(E17="","Cancellations",E17),0) -> Cancellations | V17: =IF(OR(F17<>"",N17="Cancelled"),"Cancelled","Delivered") -> Delivered | W17: =IF(V17="Cancelled",1,0) -> 0 | X17: =VLOOKUP(H17,ProductMaster!$A$1:$E$23,2,0) -> T-Shirt
A18: ORD0017 | B18: 45105 | C18: =TEXT(B18,"mmm") -> Jun | D18: =TEXT(B18,"yyy") -> 2023 | E18: 44933 | G18: CUST045 | H18: PROD015 | I18: East | J18: 21 | K18: 3 | L18: 63 | M18: Credit Card | N18: Delivered | O18: DHL | P18: =K18*J18 -> 63 | Q18: =IF(N18="Delivered",E18-B18,"") -> -172 | R18: {=_xlfn.XLOOKUP(Table1[[#This Row],[Product ID]],Table2[[#All],[Product ID]],Table2[[#All],[Category]])} -> Books | S18: {=_xlfn.XLOOKUP(Table1[[#This Row],[Customer ID]],Table4[[#All],[Customer ID]],Table4[[#All],[Customer Name]])} -> Emily Johnson | T18: =IF(E18-B18<=2,"Fast","Slow") -> Fast | U18: =IFERROR(IF(E18="","Cancellations",E18),0) -> 44933 | V18: =IF(OR(F18<>"",N18="Cancelled"),"Cancelled","Delivered") -> Delivered | W18: =IF(V18="Cancelled",1,0) -> 0 | X18: =VLOOKUP(H18,ProductMaster!$A$1:$E$23,2,0) -> Novel
A19: ORD0018 | B19: 45258 | C19: =TEXT(B19,"mmm") -> Nov | D19: =TEXT(B19,"yyy") -> 2023 | G19: CUST011 | H19: PROD008 | I19: West | J19: 70 | K19: 5 | L19: 350 | M19: PayPal | N19: In Transit | O19: Amazon Logistics | P19: =K19*J19 -> 350 | Q19: =IF(N19="Delivered",E19-B19,"") | R19: {=_xlfn.XLOOKUP(Table1[[#This Row],[Product ID]],Table2[[#All],[Product ID]],Table2[[#All],[Category]])} -> Books | S19: {=_xlfn.XLOOKUP(Table1[[#This Row],[Customer ID]],Table4[[#All],[Customer ID]],Table4[[#All],[Customer Name]])} -> Mason Hall | T19: =IF(E19-B19<=2,"Fast","Slow") -> Fast | U19: =IFERROR(IF(E19="","Cancellations",E19),0) -> Cancellations | V19: =IF(OR(F19<>"",N19="Cancelled"),"Cancelled","Delivered") -> Delivered | W19: =IF(V19="Cancelled",1,0) -> 0 | X19: =VLOOKUP(H19,ProductMaster!$A$1:$E$23,2,0) -> Textbook
A20: ORD0019 | B20: 45163 | C20: =TEXT(B20,"mmm") -> Aug | D20: =TEXT(B20,"yyy") -> 2023 | G20: CUST041 | H20: PROD006 | I20: South | J20: 94 | K20: 4 | L20: 376 | M20: Credit Card | N20: In Transit | O20: USPS | P20: =K20*J20 -> 376 | Q20: =IF(N20="Delivered",E20-B20,"") | R20: {=_xlfn.XLOOKUP(Table1[[#This Row],[Product ID]],Table2[[#All],[Product ID]],Table2[[#All],[Category]])} -> Fashion | S20: {=_xlfn.XLOOKUP(Table1[[#This Row],[Customer ID]],Table4[[#All],[Customer ID]],Table4[[#All],[Customer Name]])} -> Jacob Price | T20: =IF(E20-B20<=2,"Fast","Slow") -> Fast | U20: =IFERROR(IF(E20="","Cancellations",E20),0) -> Cancellations | V20: =IF(OR(F20<>"",N20="Cancelled"),"Cancelled","Delivered") -> Delivered | W20: =IF(V20="Cancelled",1,0) -> 0 | X20: =VLOOKUP(H20,ProductMaster!$A$1:$E$23,2,0) -> Shoes
A21: ORD0020 | B21: 45264 | C21: =TEXT(B21,"mmm") -> Dec | D21: =TEXT(B21,"yyy") -> 2023 | G21: CUST025 | H21: PROD001 | I21: North | J21: 813 | K21: 2 | L21: 1626 | M21: Credit Card | N21: In Transit | O21: FedEx | P21: =K21*J21 -> 1626 | Q21: =IF(N21="Delivered",E21-B21,"") | R21: {=_xlfn.XLOOKUP(Table1[[#This Row],[Product ID]],Table2[[#All],[Product ID]],Table2[[#All],[Category]])} -> Electronics | S21: {=_xlfn.XLOOKUP(Table1[[#This Row],[Customer ID]],Table4[[#All],[Customer ID]],Table4[[#All],[Customer Name]])} -> Emma King | T21: =IF(E21-B21<=2,"Fast","Slow") -> Fast | U21: =IFERROR(IF(E21="","Cancellations",E21),0) -> Cancellations | V21: =IF(OR(F21<>"",N21="Cancelled"),"Cancelled","Delivered") -> Delivered | W21: =IF(V21="Cancelled",1,0) -> 0 | X21: =VLOOKUP(H21,ProductMaster!$A$1:$E$23,2,0) -> Smartphone
A22: ORD0021 | B22: 44967 | C22: =TEXT(B22,"mmm") -> Feb | D22: =TEXT(B22,"yyy") -> 2023 | G22: CUST013 | H22: PROD015 | I22: Central | J22: 21 | K22: 4 | L22: 84 | M22: PayPal | N22: In Transit | O22: Amazon Logistics | P22: =K22*J22 -> 84 | Q22: =IF(N22="Delivered",E22-B22,"") | R22: {=_xlfn.XLOOKUP(Table1[[#This Row],[Product ID]],Table2[[#All],[Product ID]],Table2[[#All],[Category]])} -> Books | S22: {=_xlfn.XLOOKUP(Table1[[#This Row],[Customer ID]],Table4[[#All],[Customer ID]],Table4[[#All],[Customer Name]])} -> Olivia Martinez | T22: =IF(E22-B22<=2,"Fast","Slow") -> Fast | U22: =IFERROR(IF(E22="","Cancellations",E22),0) -> Cancellations | V22: =IF(OR(F22<>"",N22="Cancelled"),"Cancelled","Delivered") -> Delivered | W22: =IF(V22="Cancelled",1,0) -> 0 | X22: =VLOOKUP(H22,ProductMaster!$A$1:$E$23,2,0) -> Novel
A23: ORD0022 | B23: 45180 | C23: =TEXT(B23,"mmm") -> Sep | D23: =TEXT(B23,"yyy") -> 2023 | G23: CUST023 | H23: PROD012 | I23: West | J23: 46 | K23: 5 | L23: 230 | M23: PayPal | N23: In Transit | O23: USPS | P23: =K23*J23 -> 230 | Q23: =IF(N23="Delivered",E23-B23,"") | R23: {=_xlfn.XLOOKUP(Table1[[#This Row],[Product ID]],Table2[[#All],[Product ID]],Table2[[#All],[Category]])} -> Home | S23: {=_xlfn.XLOOKUP(Table1[[#This Row],[Customer ID]],Table4[[#All],[Customer ID]],Table4[[#All],[Customer Name]])} -> Charlotte Reed | T23: =IF(E23-B23<=2,"Fast","Slow") -> Fast | U23: =IFERROR(IF(E23="","Cancellations",E23),0) -> Cancellations | V23: =IF(OR(F23<>"",N23="Cancelled"),"Cancelled","Delivered") -> Delivered | W23: =IF(V23="Cancelled",1,0) -> 0 | X23: =VLOOKUP(H23,ProductMaster!$A$1:$E$23,2,0) -> Lamp
A24: ORD0023 | B24: 44970 | C24: =TEXT(B24,"mmm") -> Feb | D24: =TEXT(B24,"yyy") -> 2023 | F24: 44971 | G24: CUST016 | H24: PROD010 | I24: West | J24: 58 | K24: 3 | L24: 174 | M24: Amazon Pay | N24: Cancelled | O24: Amazon Logistics | P24: =K24*J24 -> 174 | Q24: =IF(N24="Delivered",E24-B24,"") | R24: {=_xlfn.XLOOKUP(Table1[[#This Row],[Product ID]],Table2[[#All],[Product ID]],Table2[[#All],[Category]])} -> Fashion | S24: {=_xlfn.XLOOKUP(Table1[[#This Row],[Customer ID]],Table4[[#All],[Customer ID]],Table4[[#All],[Customer Name]])} -> Elijah Lewis | T24: =IF(E24-B24<=2,"Fast","Slow") -> Fast | U24: =IFERROR(IF(E24="","Cancellations",E24),0) -> Cancellations | V24: =IF(OR(F24<>"",N24="Cancelled"),"Cancelled","Delivered") -> Cancelled | W24: =IF(V24="Cancelled",1,0) -> 1 | X24: =VLOOKUP(H24,ProductMaster!$A$1:$E$23,2,0) -> Jeans
A25: ORD0024 | B25: 44968 | C25: =TEXT(B25,"mmm") -> Feb | D25: =TEXT(B25,"yyy") -> 2023 | E25: 45057 | G25: CUST028 | H25: PROD006 | I25: West | J25: 96 | K25: 5 | L25: 480 | M25: Amazon Pay | N25: Delivered | O25: Amazon Logistics | P25: =K25*J25 -> 480 | Q25: =IF(N25="Delivered",E25-B25,"") -> 89 | R25: {=_xlfn.XLOOKUP(Table1[[#This Row],[Product ID]],Table2[[#All],[Product ID]],Table2[[#All],[Category]])} -> Fashion | S25: {=_xlfn.XLOOKUP(Table1[[#This Row],[Customer ID]],Table4[[#All],[Customer ID]],Table4[[#All],[Customer Name]])} -> Lily Bennett | T25: =IF(E25-B25<=2,"Fast","Slow") -> Slow | U25: =IFERROR(IF(E25="","Cancellations",E25),0) -> 45057 | V25: =IF(OR(F25<>"",N25="Cancelled"),"Cancelled","Delivered") -> Delivered | W25: =IF(V25="Cancelled",1,0) -> 0 | X25: =VLOOKUP(H25,ProductMaster!$A$1:$E$23,2,0) -> Shoes
A26: ORD0025 | B26: 45074 | C26: =TEXT(B26,"mmm") -> May | D26: =TEXT(B26,"yyy") -> 2023 | E26: 45076 | G26: CUST040 | H26: PROD002 | I26: South | J26: 43 | K26: 1 | L26: 43 | M26: Debit Card | N26: Delivered | O26: Amazon Logistics | P26: =K26*J26 -> 43 | Q26: =IF(N26="Delivered",E26-B26,"") -> 2 | R26: {=_xlfn.XLOOKUP(Table1[[#This Row],[Product ID]],Table2[[#All],[Product ID]],Table2[[#All],[Category]])} -> Toys | S26: {=_xlfn.XLOOKUP(Table1[[#This Row],[Customer ID]],Table4[[#All],[Customer ID]],Table4[[#All],[Customer Name]])} -> Benjamin Clark | T26: =IF(E26-B26<=2,"Fast","Slow") -> Fast | U26: =IFERROR(IF(E26="","Cancellations",E26),0) -> 45076 | V26: =IF(OR(F26<>"",N26="Cancelled"),"Cancelled","Delivered") -> Delivered | W26: =IF(V26="Cancelled",1,0) -> 0 | X26: =VLOOKUP(H26,ProductMaster!$A$1:$E$23,2,0) -> Action Figure
A27: ORD0026 | B27: 45214 | C27: =TEXT(B27,"mmm") -> Oct | D27: =TEXT(B27,"yyy") -> 2023 | E27: 45220 | G27: CUST027 | H27: PROD022 | I27: South | J27: 64 | K27: 4 | L27: 256 | M27: Debit Card | N27: Delivered | O27: USPS | P27: =K27*J27 -> 256 | Q27: =IF(N27="Delivered",E27-B27,"") -> 6 | R27: {=_xlfn.XLOOKUP(Table1[[#This Row],[Product ID]],Table2[[#All],[Product ID]],Table2[[#All],[Category]])} -> Fashion | S27: {=_xlfn.XLOOKUP(Table1[[#This Row],[Customer ID]],Table4[[#All],[Customer ID]],Table4[[#All],[Customer Name]])} -> Hazel Brooks | T27: =IF(E27-B27<=2,"Fast","Slow") -> Slow | U27: =IFERROR(IF(E27="","Cancellations",E27),0) -> 45220 | V27: =IF(OR(F27<>"",N27="Cancelled"),"Cancelled","Delivered") -> Delivered | W27: =IF(V27="Cancelled",1,0) -> 0 | X27: =VLOOKUP(H27,ProductMaster!$A$1:$E$23,2,0) -> Backpack
A28: ORD0027 | B28: 44942 | C28: =TEXT(B28,"mmm") -> Jan | D28: =TEXT(B28,"yyy") -> 2023 | G28: CUST018 | H28: PROD008 | I28: South | J28: 70 | K28: 2 | L28: 140 | M28: Amazon Pay | N28: In Transit | O28: Amazon Logistics | P28: =K28*J28 -> 140 | Q28: =IF(N28="Delivered",E28-B28,"") | R28: {=_xlfn.XLOOKUP(Table1[[#This Row],[Product ID]],Table2[[#All],[Product ID]],Table2[[#All],[Category]])} -> Books | S28: {=_xlfn.XLOOKUP(Table1[[#This Row],[Customer ID]],Table4[[#All],[Customer ID]],Table4[[#All],[Customer Name]])} -> Grace Scott | T28: =IF(E28-B28<=2,"Fast","Slow") -> Fast | U28: =IFERROR(IF(E28="","Cancellations",E28),0) -> Cancellations | V28: =IF(OR(F28<>"",N28="Cancelled"),"Cancelled","Delivered") -> Delivered | W28: =IF(V28="Cancelled",1,0) -> 0 | X28: =VLOOKUP(H28,ProductMaster!$A$1:$E$23,2,0) -> Textbook
A29: ORD0028 | B29: 45179 | C29: =TEXT(B29,"mmm") -> Sep | D29: =TEXT(B29,"yyy") -> 2023 | G29: CUST018 | H29: PROD018 | I29: Central | J29: 97 | K29: 3 | L29: 291 | M29: Credit Card | N29: In Transit | O29: Amazon Logistics | P29: =K29*J29 -> 291 | Q29: =IF(N29="Delivered",E29-B29,"") | R29: {=_xlfn.XLOOKUP(Table1[[#This Row],[Product ID]],Table2[[#All],[Product ID]],Table2[[#All],[Category]])} -> Toys | S29: {=_xlfn.XLOOKUP(Table1[[#This Row],[Customer ID]],Table4[[#All],[Customer ID]],Table4[[#All],[Customer Name]])} -> Grace Scott | T29: =IF(E29-B29<=2,"Fast","Slow") -> Fast | U29: =IFERROR(IF(E29="","Cancellations",E29),0) -> Cancellations | V29: =IF(OR(F29<>"",N29="Cancelled"),"Cancelled","Delivered") -> Delivered | W29: =IF(V29="Cancelled",1,0) -> 0 | X29: =VLOOKUP(H29,ProductMaster!$A$1:$E$23,2,0) -> Doll House
A30: ORD0029 | B30: 45117 | C30: =TEXT(B30,"mmm") -> Jul | D30: =TEXT(B30,"yyy") -> 2023 | F30: 45209 | G30: CUST007 | H30: PROD021 | I30: East | J30: 37 | K30: 3 | L30: 111 | M30: Apple Pay | N30: Cancelled | O30: DHL | P30: =K30*J30 -> 111 | Q30: =IF(N30="Delivered",E30-B30,"") | R30: {=_xlfn.XLOOKUP(Table1[[#This Row],[Product ID]],Table2[[#All],[Product ID]],Table2[[#All],[Category]])} -> Home | S30: {=_xlfn.XLOOKUP(Table1[[#This Row],[Customer ID]],Table4[[#All],[Customer ID]],Table4[[#All],[Customer Name]])} -> Liam Walker | T30: =IF(E30-B30<=2,"Fast","Slow") -> Fast | U30: =IFERROR(IF(E30="","Cancellations",E30),0) -> Cancellations | V30: =IF(OR(F30<>"",N30="Cancelled"),"Cancelled","Delivered") -> Cancelled | W30: =IF(V30="Cancelled",1,0) -> 1 | X30: =VLOOKUP(H30,ProductMaster!$A$1:$E$23,2,0) -> Wall Clock
A31: ORD0030 | B31: 44971 | C31: =TEXT(B31,"mmm") -> Feb | D31: =TEXT(B31,"yyy") -> 2023 | G31: CUST008 | H31: PROD008 | I31: North | J31: 69 | K31: 5 | L31: 345 | M31: Amazon Pay | N31: In Transit | O31: Amazon Logistics | P31: =K31*J31 -> 345 | Q31: =IF(N31="Delivered",E31-B31,"") | R31: {=_xlfn.XLOOKUP(Table1[[#This Row],[Product ID]],Table2[[#All],[Product ID]],Table2[[#All],[Category]])} -> Books | S31: {=_xlfn.XLOOKUP(Table1[[#This Row],[Customer ID]],Table4[[#All],[Customer ID]],Table4[[#All],[Customer Name]])} -> Harper Young | T31: =IF(E31-B31<=2,"Fast","Slow") -> Fast | U31: =IFERROR(IF(E31="","Cancellations",E31),0) -> Cancellations | V31: =IF(OR(F31<>"",N31="Cancelled"),"Cancelled","Delivered") -> Delivered | W31: =IF(V31="Cancelled",1,0) -> 0 | X31: =VLOOKUP(H31,ProductMaster!$A$1:$E$23,2,0) -> Textbook
A32: ORD0031 | B32: 45011 | C32: =TEXT(B32,"mmm") -> Mar | D32: =TEXT(B32,"yyy") -> 2023 | G32: CUST014 | H32: PROD002 | I32: North | J32: 42 | K32: 5 | L32: 210 | M32: Amazon Pay | N32: In Transit | O32: UPS | P32: =K32*J32 -> 210 | Q32: =IF(N32="Delivered",E32-B32,"") | R32: {=_xlfn.XLOOKUP(Table1[[#This Row],[Product ID]],Table2[[#All],[Product ID]],Table2[[#All],[Category]])} -> Toys | S32: {=_xlfn.XLOOKUP(Table1[[#This Row],[Customer ID]],Table4[[#All],[Customer ID]],Table4[[#All],[Customer Name]])} -> Harper Young | T32: =IF(E32-B32<=2,"Fast","Slow") -> Fast | U32: =IFERROR(IF(E32="","Cancellations",E32),0) -> Cancellations | V32: =IF(OR(F32<>"",N32="Cancelled"),"Cancelled","Delivered") -> Delivered | W32: =IF(V32="Cancelled",1,0) -> 0 | X32: =VLOOKUP(H32,ProductMaster!$A$1:$E$23,2,0) -> Action Figure
A33: ORD0032 | B33: 45092 | C33: =TEXT(B33,"mmm") -> Jun | D33: =TEXT(B33,"yyy") -> 2023 | F33: 45099 | G33: CUST037 | H33: PROD009 | I33: East | J33: 11 | K33: 5 | L33: 55 | M33: Debit Card | N33: Cancelled | O33: FedEx | P33: =K33*J33 -> 55 | Q33: =IF(N33="Delivered",E33-B33,"") | R33: {=_xlfn.XLOOKUP(Table1[[#This Row],[Product ID]],Table2[[#All],[Product ID]],Table2[[#All],[Category]])} -> Books | S33: {=_xlfn.XLOOKUP(Table1[[#This Row],[Customer ID]],Table4[[#All],[Customer ID]],Table4[[#All],[Customer Name]])} -> Emily Johnson | T33: =IF(E33-B33<=2,"Fast","Slow") -> Fast | U33: =IFERROR(IF(E33="","Cancellations",E33),0) -> Cancellations | V33: =IF(OR(F33<>"",N33="Cancelled"),"Cancelled","Delivered") -> Cancelled | W33: =IF(V33="Cancelled",1,0) -> 1 | X33: =VLOOKUP(H33,ProductMaster!$A$1:$E$23,2,0) -> Magazine
A34: ORD0033 | B34: 45068 | C34: =TEXT(B34,"mmm") -> May | D34: =TEXT(B34,"yyy") -> 2023 | E34: 45069 | G34: CUST016 | H34: PROD005 | I34: South | J34: 27 | K34: 2 | L34: 54 | M34: Apple Pay | N34: Delivered | O34: USPS | P34: =K34*J34 -> 54 | Q34: =IF(N34="Delivered",E34-B34,"") -> 1 | R34: {=_xlfn.XLOOKUP(Table1[[#This Row],[Product ID]],Table2[[#All],[Product ID]],Table2[[#All],[Category]])} -> Fashion | S34: {=_xlfn.XLOOKUP(Table1[[#This Row],[Customer ID]],Table4[[#All],[Customer ID]],Table4[[#All],[Customer Name]])} -> Elijah Lewis | T34: =IF(E34-B34<=2,"Fast","Slow") -> Fast | U34: =IFERROR(IF(E34="","Cancellations",E34),0) -> 45069 | V34: =IF(OR(F34<>"",N34="Cancelled"),"Cancelled","Delivered") -> Delivered | W34: =IF(V34="Cancelled",1,0) -> 0 | X34: =VLOOKUP(H34,ProductMaster!$A$1:$E$23,2,0) -> T-Shirt
A35: ORD0034 | B35: 45250 | C35: =TEXT(B35,"mmm") -> Nov | D35: =TEXT(B35,"yyy") -> 2023 | G35: CUST025 | H35: PROD015 | I35: South | J35: 21 | K35: 1 | L35: 21 | M35: Amazon Pay | N35: In Transit | O35: DHL | P35: =K35*J35 -> 21 | Q35: =IF(N35="Delivered",E35-B35,"") | R35: {=_xlfn.XLOOKUP(Table1[[#This Row],[Product ID]],Table2[[#All],[Product ID]],Table2[[#All],[Category]])} -> Books | S35: {=_xlfn.XLOOKUP(Table1[[#This Row],[Customer ID]],Table4[[#All],[Customer ID]],Table4[[#All],[Customer Name]])} -> Emma King | T35: =IF(E35-B35<=2,"Fast","Slow") -> Fast | U35: =IFERROR(IF(E35="","Cancellations",E35),0) -> Cancellations | V35: =IF(OR(F35<>"",N35="Cancelled"),"Cancelled","Delivered") -> Delivered | W35: =IF(V35="Cancelled",1,0) -> 0 | X35: =VLOOKUP(H35,ProductMaster!$A$1:$E$23,2,0) -> Novel
A36: ORD0035 | B36: 45282 | C36: =TEXT(B36,"mmm") -> Dec | D36: =TEXT(B36,"yyy") -> 2023 | E36: 45286 | G36: CUST032 | H36: PROD011 | I36: South | J36: 172 | K36: 1 | L36: 172 | M36: PayPal | N36: Delivered | O36: USPS | P36: =K36*J36 -> 172 | Q36: =IF(N36="Delivered",E36-B36,"") -> 4 | R36: {=_xlfn.XLOOKUP(Table1[[#This Row],[Product ID]],Table2[[#All],[Product ID]],Table2[[#All],[Category]])} -> Electronics | S36: {=_xlfn.XLOOKUP(Table1[[#This Row],[Customer ID]],Table4[[#All],[Customer ID]],Table4[[#All],[Customer Name]])} -> Luke Gray | T36: =IF(E36-B36<=2,"Fast","Slow") -> Slow | U36: =IFERROR(IF(E36="","Cancellations",E36),0) -> 45286 | V36: =IF(OR(F36<>"",N36="Cancelled"),"Cancelled","Delivered") -> Delivered | W36: =IF(V36="Cancelled",1,0) -> 0 | X36: =VLOOKUP(H36,ProductMaster!$A$1:$E$23,2,0) -> Headphones
A37: ORD0036 | B37: 45130 | C37: =TEXT(B37,"mmm") -> Jul | D37: =TEXT(B37,"yyy") -> 2023 | G37: CUST014 | H37: PROD016 | I37: North | J37: 212 | K37: 3 | L37: 636 | M37: Amazon Pay | N37: In Transit | O37: UPS | P37: =K37*J37 -> 636 | Q37: =IF(N37="Delivered",E37-B37,"") | R37: {=_xlfn.XLOOKUP(Table1[[#This Row],[Product ID]],Table2[[#All],[Product ID]],Table2[[#All],[Category]])} -> Home | S37: {=_xlfn.XLOOKUP(Table1[[#This Row],[Customer ID]],Table4[[#All],[Customer ID]],Table4[[#All],[Customer Name]])} -> Harper Young | T37: =IF(E37-B37<=2,"Fast","Slow") -> Fast | U37: =IFERROR(IF(E37="","Cancellations",E37),0) -> Cancellations | V37: =IF(OR(F37<>"",N37="Cancelled"),"Cancelled","Delivered") -> Delivered | W37: =IF(V37="Cancelled",1,0) -> 0 | X37: =VLOOKUP(H37,ProductMaster!$A$1:$E$23,2,0) -> Cookware Set Pro
A38: ORD0037 | B38: 45216 | C38: =TEXT(B38,"mmm") -> Oct | D38: =TEXT(B38,"yyy") -> 2023 | E38: 45221 | G38: CUST044 | H38: PROD002 | I38: East | J38: 41 | K38: 4 | L38: 164 | M38: Credit Card | N38: Delivered | O38: Amazon Logistics | P38: =K38*J38 -> 164 | Q38: =IF(N38="Delivered",E38-B38,"") -> 5 | R38: {=_xlfn.XLOOKUP(Table1[[#This Row],[Product ID]],Table2[[#All],[Product ID]],Table2[[#All],[Category]])} -> Toys | S38: {=_xlfn.XLOOKUP(Table1[[#This Row],[Customer ID]],Table4[[#All],[Customer ID]],Table4[[#All],[Customer Name]])} -> Grace Ward | T38: =IF(E38-B38<=2,"Fast","Slow") -> Slow | U38: =IFERROR(IF(E38="","Cancellations",E38),0) -> 45221 | V38: =IF(OR(F38<>"",N38="Cancelled"),"Cancelled","Delivered") -> Delivered | W38: =IF(V38="Cancelled",1,0) -> 0 | X38: =VLOOKUP(H38,ProductMaster!$A$1:$E$23,2,0) -> Action Figure
A39: ORD0038 | B39: 45160 | C39: =TEXT(B39,"mmm") -> Aug | D39: =TEXT(B39,"yyy") -> 2023 | F39: 45162 | G39: CUST028 | H39: PROD007 | I39: North | J39: 32 | K39: 2 | L39: 64 | M39: Debit Card | N39: Cancelled | O39: FedEx | P39: =K39*J39 -> 64 | Q39: =IF(N39="Delivered",E39-B39,"") | R39: {=_xlfn.XLOOKUP(Table1[[#This Row],[Product ID]],Table2[[#All],[Product ID]],Table2[[#All],[Category]])} -> Toys | S39: {=_xlfn.XLOOKUP(Table1[[#This Row],[Customer ID]],Table4[[#All],[Customer ID]],Table4[[#All],[Customer Name]])} -> Lily Bennett | T39: =IF(E39-B39<=2,"Fast","Slow") -> Fast | U39: =IFERROR(IF(E39="","Cancellations",E39),0) -> Cancellations | V39: =IF(OR(F39<>"",N39="Cancelled"),"Cancelled","Delivered") -> Cancelled | W39: =IF(V39="Cancelled",1,0) -> 1 | X39: =VLOOKUP(H39,ProductMaster!$A$1:$E$23,2,0) -> Puzzle
A40: ORD0039 | B40: 44969 | C40: =TEXT(B40,"mmm") -> Feb | D40: =TEXT(B40,"yyy") -> 2023 | G40: CUST024 | H40: PROD022 | I40: East | J40: 66 | K40: 2 | L40: 132 | M40: Apple Pay | N40: In Transit | O40: DHL | P40: =K40*J40 -> 132 | Q40: =IF(N40="Delivered",E40-B40,"") | R40: {=_xlfn.XLOOKUP(Table1[[#This Row],[Product ID]],Table2[[#All],[Product ID]],Table2[[#All],[Category]])} -> Fashion | S40: {=_xlfn.XLOOKUP(Table1[[#This Row],[Customer ID]],Table4[[#All],[Customer ID]],Table4[[#All],[Customer Name]])} -> Scarlett Murphy | T40: =IF(E40-B40<=2,"Fast","Slow") -> Fast | U40: =IFERROR(IF(E40="","Cancellations",E40),0) -> Cancellations | V40: =IF(OR(F40<>"",N40="Cancelled"),"Cancelled","Delivered") -> Delivered | W40: =IF(V40="Cancelled",1,0) -> 0 | X40: =VLOOKUP(H40,ProductMaster!$A$1:$E$23,2,0) -> Backpack
A41: ORD0040 | B41: 45285 | C41: =TEXT(B41,"mmm") -> Dec | D41: =TEXT(B41,"yyy") -> 2023 | G41: CUST006 | H41: PROD004 | I41: East | J41: 62 | K41: 4 | L41: 248 | M41: Debit Card | N41: In Transit | O41: UPS | P41: =K41*J41 -> 248 | Q41: =IF(N41="Delivered",E41-B41,"") | R41: {=_xlfn.XLOOKUP(Table1[[#This Row],[Product ID]],Table2[[#All],[Product ID]],Table2[[#All],[Category]])} -> Toys | S41: {=_xlfn.XLOOKUP(Table1[[#This Row],[Customer ID]],Table4[[#All],[Customer ID]],Table4[[#All],[Customer Name]])} -> Ava Robinson | T41: =IF(E41-B41<=2,"Fast","Slow") -> Fast | U41: =IFERROR(IF(E41="","Cancellations",E41),0) -> Cancellations | V41: =IF(OR(F41<>"",N41="Cancelled"),"Cancelled","Delivered") -> Delivered | W41: =IF(V41="Cancelled",1,0) -> 0 | X41: =VLOOKUP(H41,ProductMaster!$A$1:$E$23,2,0) -> Leg Set
A42: ORD0041 | B42: 45192 | C42: =TEXT(B42,"mmm") -> Sep | D42: =TEXT(B42,"yyy") -> 2023 | E42: 45199 | G42: CUST001 | H42: PROD011 | I42: West | J42: 173 | K42: 4 | L42: 692 | M42: Apple Pay | N42: Delivered | O42: UPS | P42: =K42*J42 -> 692 | Q42: =IF(N42="Delivered",E42-B42,"") -> 7 | R42: {=_xlfn.XLOOKUP(Table1[[#This Row],[Product ID]],Table2[[#All],[Product ID]],Table2[[#All],[Category]])} -> Electronics | S42: {=_xlfn.XLOOKUP(Table1[[#This Row],[Customer ID]],Table4[[#All],[Customer ID]],Table4[[#All],[Customer Name]])} -> James Miller | T42: =IF(E42-B42<=2,"Fast","Slow") -> Slow | U42: =IFERROR(IF(E42="","Cancellations",E42),0) -> 45199 | V42: =IF(OR(F42<>"",N42="Cancelled"),"Cancelled","Delivered") -> Delivered | W42: =IF(V42="Cancelled",1,0) -> 0 | X42: =VLOOKUP(H42,ProductMaster!$A$1:$E$23,2,0) -> Headphones
A43: ORD0042 | B43: 45123 | C43: =TEXT(B43,"mmm") -> Jul | D43: =TEXT(B43,"yyy") -> 2023 | E43: 45125 | G43: CUST007 | H43: PROD004 | I43: West | J43: 63 | K43: 3 | L43: 189 | M43: Apple Pay | N43: Delivered | O43: UPS | P43: =K43*J43 -> 189 | Q43: =IF(N43="Delivered",E43-B43,"") -> 2 | R43: {=_xlfn.XLOOKUP(Table1[[#This Row],[Product ID]],Table2[[#All],[Product ID]],Table2[[#All],[Category]])} -> Toys | S43: {=_xlfn.XLOOKUP(Table1[[#This Row],[Customer ID]],Table4[[#All],[Customer ID]],Table4[[#All],[Customer Name]])} -> Liam Walker | T43: =IF(E43-B43<=2,"Fast","Slow") -> Fast | U43: =IFERROR(IF(E43="","Cancellations",E43),0) -> 45125 | V43: =IF(OR(F43<>"",N43="Cancelled"),"Cancelled","Delivered") -> Delivered | W43: =IF(V43="Cancelled",1,0) -> 0 | X43: =VLOOKUP(H43,ProductMaster!$A$1:$E$23,2,0) -> Leg Set
A44: ORD0043 | B44: 45048 | C44: =TEXT(B44,"mmm") -> May | D44: =TEXT(B44,"yyy") -> 2023 | F44: 45232 | G44: CUST040 | H44: PROD021 | I44: West | J44: 36 | K44: 3 | L44: 108 | M44: Debit Card | N44: Cancelled | O44: USPS | P44: =K44*J44 -> 108 | Q44: =IF(N44="Delivered",E44-B44,"") | R44: {=_xlfn.XLOOKUP(Table1[[#This Row],[Product ID]],Table2[[#All],[Product ID]],Table2[[#All],[Category]])} -> Home | S44: {=_xlfn.XLOOKUP(Table1[[#This Row],[Customer ID]],Table4[[#All],[Customer ID]],Table4[[#All],[Customer Name]])} -> Benjamin Clark | T44: =IF(E44-B44<=2,"Fast","Slow") -> Fast | U44: =IFERROR(IF(E44="","Cancellations",E44),0) -> Cancellations | V44: =IF(OR(F44<>"",N44="Cancelled"),"Cancelled","Delivered") -> Cancelled | W44: =IF(V44="Cancelled",1,0) -> 1 | X44: =VLOOKUP(H44,ProductMaster!$A$1:$E$23,2,0) -> Wall Clock
A45: ORD0044 | B45: 45278 | C45: =TEXT(B45,"mmm") -> Dec | D45: =TEXT(B45,"yyy") -> 2023 | F45: 45283 | G45: CUST006 | H45: PROD004 | I45: Central | J45: 62 | K45: 1 | L45: 62 | M45: Apple Pay | N45: Cancelled | O45: Amazon Logistics | P45: =K45*J45 -> 62 | Q45: =IF(N45="Delivered",E45-B45,"") | R45: {=_xlfn.XLOOKUP(Table1[[#This Row],[Product ID]],Table2[[#All],[Product ID]],Table2[[#All],[Category]])} -> Toys | S45: {=_xlfn.XLOOKUP(Table1[[#This Row],[Customer ID]],Table4[[#All],[Customer ID]],Table4[[#All],[Customer Name]])} -> Ava Robinson | T45: =IF(E45-B45<=2,"Fast","Slow") -> Fast | U45: =IFERROR(IF(E45="","Cancellations",E45),0) -> Cancellations | V45: =IF(OR(F45<>"",N45="Cancelled"),"Cancelled","Delivered") -> Cancelled | W45: =IF(V45="Cancelled",1,0) -> 1 | X45: =VLOOKUP(H45,ProductMaster!$A$1:$E$23,2,0) -> Leg Set
A46: ORD0045 | B46: 45236 | C46: =TEXT(B46,"mmm") -> Nov | D46: =TEXT(B46,"yyy") -> 2023 | F46: 45091 | G46: CUST042 | H46: PROD003 | I46: Central | J46: 137 | K46: 5 | L46: 685 | M46: Amazon Pay | N46: Cancelled | O46: FedEx | P46: =K46*J46 -> 685 | Q46: =IF(N46="Delivered",E46-B46,"") | R46: {=_xlfn.XLOOKUP(Table1[[#This Row],[Product ID]],Table2[[#All],[Product ID]],Table2[[#All],[Category]])} -> Home | S46: {=_xlfn.XLOOKUP(Table1[[#This Row],[Customer ID]],Table4[[#All],[Customer ID]],Table4[[#All],[Customer Name]])} -> Noah Wilson | T46: =IF(E46-B46<=2,"Fast","Slow") -> Fast | U46: =IFERROR(IF(E46="","Cancellations",E46),0) -> Cancellations | V46: =IF(OR(F46<>"",N46="Cancelled"),"Cancelled","Delivered") -> Cancelled | W46: =IF(V46="Cancelled",1,0) -> 1 | X46: =VLOOKUP(H46,ProductMaster!$A$1:$E$23,2,0) -> Cookware Set
A47: ORD0046 | B47: 45028 | C47: =TEXT(B47,"mmm") -> Apr | D47: =TEXT(B47,"yyy") -> 2023 | E47: 45150 | G47: CUST039 | H47: PROD017 | I47: North | J47: 73 | K47: 4 | L47: 292 | M47: Credit Card | N47: Delivered | O47: Amazon Logistics | P47: =K47*J47 -> 292 | Q47: =IF(N47="Delivered",E47-B47,"") -> 122 | R47: {=_xlfn.XLOOKUP(Table1[[#This Row],[Product ID]],Table2[[#All],[Product ID]],Table2[[#All],[Category]])} -> Electronics | S47: {=_xlfn.XLOOKUP(Table1[[#This Row],[Customer ID]],Table4[[#All],[Customer ID]],Table4[[#All],[Customer Name]])} -> Logan Ramirez | T47: =IF(E47-B47<=2,"Fast","Slow") -> Slow | U47: =IFERROR(IF(E47="","Cancellations",E47),0) -> 45150 | V47: =IF(OR(F47<>"",N47="Cancelled"),"Cancelled","Delivered") -> Delivered | W47: =IF(V47="Cancelled",1,0) -> 0 | X47: =VLOOKUP(H47,ProductMaster!$A$1:$E$23,2,0) -> Gaming Mouse
A48: ORD0047 | B48: 45124 | C48: =TEXT(B48,"mmm") -> Jul | D48: =TEXT(B48,"yyy") -> 2023 | E48: 45126 | G48: CUST041 | H48: PROD020 | I48: North | J48: 104 | K48: 1 | L48: 104 | M48: PayPal | N48: Delivered | O48: Amazon Logistics | P48: =K48*J48 -> 104 | Q48: =IF(N48="Delivered",E48-B48,"") -> 2 | R48: {=_xlfn.XLOOKUP(Table1[[#This Row],[Product ID]],Table2[[#All],[Product ID]],Table2[[#All],[Category]])} -> Electronics | S48: {=_xlfn.XLOOKUP(Table1[[#This Row],[Customer ID]],Table4[[#All],[Customer ID]],Table4[[#All],[Customer Name]])} -> Jacob Price | T48: =IF(E48-B48<=2,"Fast","Slow") -> Fast | U48: =IFERROR(IF(E48="","Cancellations",E48),0) -> 45126 | V48: =IF(OR(F48<>"",N48="Cancelled"),"Cancelled","Delivered") -> Delivered | W48: =IF(V48="Cancelled",1,0) -> 0 | X48: =VLOOKUP(H48,ProductMaster!$A$1:$E$23,2,0) -> Bluetooth Speaker
A49: ORD0048 | B49: 45218 | C49: =TEXT(B49,"mmm") -> Oct | D49: =TEXT(B49,"yyy") -> 2023 | E49: 45223 | G49: CUST044 | H49: PROD006 | I49: East | J49: 97 | K49: 1 | L49: 97 | M49: Amazon Pay | N49: Delivered | O49: FedEx | P49: =K49*J49 -> 97 | Q49: =IF(N49="Delivered",E49-B49,"") -> 5 | R49: {=_xlfn.XLOOKUP(Table1[[#This Row],[Product ID]],Table2[[#All],[Product ID]],Table2[[#All],[Category]])} -> Fashion | S49: {=_xlfn.XLOOKUP(Table1[[#This Row],[Customer ID]],Table4[[#All],[Customer ID]],Table4[[#All],[Customer Name]])} -> Grace Ward | T49: =IF(E49-B49<=2,"Fast","Slow") -> Slow | U49: =IFERROR(IF(E49="","Cancellations",E49),0) -> 45223 | V49: =IF(OR(F49<>"",N49="Cancelled"),"Cancelled","Delivered") -> Delivered | W49: =IF(V49="Cancelled",1,0) -> 0 | X49: =VLOOKUP(H49,ProductMaster!$A$1:$E$23,2,0) -> Shoes
A50: ORD0049 | B50: 45061 | C50: =TEXT(B50,"mmm") -> May | D50: =TEXT(B50,"yyy") -> 2023 | G50: CUST026 | H50: PROD017 | I50: South | J50: 73 | K50: 5 | L50: 365 | M50: Apple Pay | N50: In Transit | O50: Amazon Logistics | P50: =K50*J50 -> 365 | Q50: =IF(N50="Delivered",E50-B50,"") | R50: {=_xlfn.XLOOKUP(Table1[[#This Row],[Product ID]],Table2[[#All],[Product ID]],Table2[[#All],[Category]])} -> Electronics | S50: {=_xlfn.XLOOKUP(Table1[[#This Row],[Customer ID]],Table4[[#All],[Customer ID]],Table4[[#All],[Customer Name]])} -> Zoe Mitchell | T50: =IF(E50-B50<=2,"Fast","Slow") -> Fast | U50: =IFERROR(IF(E50="","Cancellations",E50),0) -> Cancellations | V50: =IF(OR(F50<>"",N50="Cancelled"),"Cancelled","Delivered") -> Delivered | W50: =IF(V50="Cancelled",1,0) -> 0 | X50: =VLOOKUP(H50,ProductMaster!$A$1:$E$23,2,0) -> Gaming Mouse
A51: ORD0050 | B51: 45262 | C51: =TEXT(B51,"mmm") -> Dec | D51: =TEXT(B51,"yyy") -> 2023 | E51: 44976 | G51: CUST040 | H51: PROD005 | I51: East | J51: 27 | K51: 3 | L51: 81 | M51: Amazon Pay | N51: Delivered | O51: UPS | P51: =K51*J51 -> 81 | Q51: =IF(N51="Delivered",E51-B51,"") -> -286 | R51: {=_xlfn.XLOOKUP(Table1[[#This Row],[Product ID]],Table2[[#All],[Product ID]],Table2[[#All],[Category]])} -> Fashion | S51: {=_xlfn.XLOOKUP(Table1[[#This Row],[Customer ID]],Table4[[#All],[Customer ID]],Table4[[#All],[Customer Name]])} -> Benjamin Clark | T51: =IF(E51-B51<=2,"Fast","Slow") -> Fast | U51: =IFERROR(IF(E51="","Cancellations",E51),0) -> 44976 | V51: =IF(OR(F51<>"",N51="Cancelled"),"Cancelled","Delivered") -> Delivered | W51: =IF(V51="Cancelled",1,0) -> 0 | X51: =VLOOKUP(H51,ProductMaster!$A$1:$E$23,2,0) -> T-Shirt
A52: ORD0051 | B52: 44967 | C52: =TEXT(B52,"mmm") -> Feb | D52: =TEXT(B52,"yyy") -> 2023 | G52: CUST041 | H52: PROD021 | I52: North | J52: 37 | K52: 1 | L52: 37 | M52: Apple Pay | N52: In Transit | O52: UPS | P52: =K52*J52 -> 37 | Q52: =IF(N52="Delivered",E52-B52,"") | R52: {=_xlfn.XLOOKUP(Table1[[#This Row],[Product ID]],Table2[[#All],[Product ID]],Table2[[#All],[Category]])} -> Home | S52: {=_xlfn.XLOOKUP(Table1[[#This Row],[Customer ID]],Table4[[#All],[Customer ID]],Table4[[#All],[Customer Name]])} -> Jacob Price | T52: =IF(E52-B52<=2,"Fast","Slow") -> Fast | U52: =IFERROR(IF(E52="","Cancellations",E52),0) -> Cancellations | V52: =IF(OR(F52<>"",N52="Cancelled"),"Cancelled","Delivered") -> Delivered | W52: =IF(V52="Cancelled",1,0) -> 0 | X52: =VLOOKUP(H52,ProductMaster!$A$1:$E$23,2,0) -> Wall Clock
A53: ORD0052 | B53: 44956 | C53: =TEXT(B53,"mmm") -> Jan | D53: =TEXT(B53,"yyy") -> 2023 | E53: 44928 | G53: CUST008 | H53: PROD015 | I53: North | J53: 22 | K53: 1 | L53: 22 | M53: Debit Card | N53: Delivered | O53: FedEx | P53: =K53*J53 -> 22 | Q53: =IF(N53="Delivered",E53-B53,"") -> -28 | R53: {=_xlfn.XLOOKUP(Table1[[#This Row],[Product ID]],Table2[[#All],[Product ID]],Table2[[#All],[Category]])} -> Books | S53: {=_xlfn.XLOOKUP(Table1[[#This Row],[Customer ID]],Table4[[#All],[Customer ID]],Table4[[#All],[Customer Name]])} -> Harper Young | T53: =IF(E53-B53<=2,"Fast","Slow") -> Fast | U53: =IFERROR(IF(E53="","Cancellations",E53),0) -> 44928 | V53: =IF(OR(F53<>"",N53="Cancelled"),"Cancelled","Delivered") -> Delivered | W53: =IF(V53="Cancelled",1,0) -> 0 | X53: =VLOOKUP(H53,ProductMaster!$A$1:$E$23,2,0) -> Novel
A54: ORD0053 | B54: 45289 | C54: =TEXT(B54,"mmm") -> Dec | D54: =TEXT(B54,"yyy") -> 2023 | E54: 45292 | G54: CUST011 | H54: PROD016 | I54: Central | J54: 218 | K54: 5 | L54: 1090 | M54: PayPal | N54: Delivered | O54: DHL | P54: =K54*J54 -> 1090 | Q54: =IF(N54="Delivered",E54-B54,"") -> 3 | R54: {=_xlfn.XLOOKUP(Table1[[#This Row],[Product ID]],Table2[[#All],[Product ID]],Table2[[#All],[Category]])} -> Home | S54: {=_xlfn.XLOOKUP(Table1[[#This Row],[Customer ID]],Table4[[#All],[Customer ID]],Table4[[#All],[Customer Name]])} -> Mason Hall | T54: =IF(E54-B54<=2,"Fast","Slow") -> Slow | U54: =IFERROR(IF(E54="","Cancellations",E54),0) -> 45292 | V54: =IF(OR(F54<>"",N54="Cancelled"),"Cancelled","Delivered") -> Delivered | W54: =IF(V54="Cancelled",1,0) -> 0 | X54: =VLOOKUP(H54,ProductMaster!$A$1:$E$23,2,0) -> Cookware Set Pro
A55: ORD0054 | B55: 45080 | C55: =TEXT(B55,"mmm") -> Jun | D55: =TEXT(B55,"yyy") -> 2023 | F55: 44998 | G55: CUST018 | H55: PROD004 | I55: North | J55: 64 | K55: 1 | L55: 64 | M55: Apple Pay | N55: Cancelled | O55: USPS | P55: =K55*J55 -> 64 | Q55: =IF(N55="Delivered",E55-B55,"") | R55: {=_xlfn.XLOOKUP(Table1[[#This Row],[Product ID]],Table2[[#All],[Product ID]],Table2[[#All],[Category]])} -> Toys | S55: {=_xlfn.XLOOKUP(Table1[[#This Row],[Customer ID]],Table4[[#All],[Customer ID]],Table4[[#All],[Customer Name]])} -> Grace Scott | T55: =IF(E55-B55<=2,"Fast","Slow") -> Fast | U55: =IFERROR(IF(E55="","Cancellations",E55),0) -> Cancellations | V55: =IF(OR(F55<>"",N55="Cancelled"),"Cancelled","Delivered") -> Cancelled | W55: =IF(V55="Cancelled",1,0) -> 1 | X55: =VLOOKUP(H55,ProductMaster!$A$1:$E$23,2,0) -> Leg Set
A56: ORD0055 | B56: 44959 | C56: =TEXT(B56,"mmm") -> Feb | D56: =TEXT(B56,"yyy") -> 2023 | E56: 45079 | G56: CUST037 | H56: PROD021 | I56: Central | J56: 36 | K56: 4 | L56: 144 | M56: PayPal | N56: Delivered | O56: Amazon Logistics | P56: =K56*J56 -> 144 | Q56: =IF(N56="Delivered",E56-B56,"") -> 120 | R56: {=_xlfn.XLOOKUP(Table1[[#This Row],[Product ID]],Table2[[#All],[Product ID]],Table2[[#All],[Category]])} -> Home | S56: {=_xlfn.XLOOKUP(Table1[[#This Row],[Customer ID]],Table4[[#All],[Customer ID]],Table4[[#All],[Customer Name]])} -> Emily Johnson | T56: =IF(E56-B56<=2,"Fast","Slow") -> Slow | U56: =IFERROR(IF(E56="","Cancellations",E56),0) -> 45079 | V56: =IF(OR(F56<>"",N56="Cancelled"),"Cancelled","Delivered") -> Delivered | W56: =IF(V56="Cancelled",1,0) -> 0 | X56: =VLOOKUP(H56,ProductMaster!$A$1:$E$23,2,0) -> Wall Clock
A57: ORD0056 | B57: 45217 | C57: =TEXT(B57,"mmm") -> Oct | D57: =TEXT(B57,"yyy") -> 2023 | E57: 45220 | G57: CUST017 | H57: PROD004 | I57: West | J57: 65 | K57: 1 | L57: 65 | M57: Amazon Pay | N57: Delivered | O57: FedEx | P57: =K57*J57 -> 65 | Q57: =IF(N57="Delivered",E57-B57,"") -> 3 | R57: {=_xlfn.XLOOKUP(Table1[[#This Row],[Product ID]],Table2[[#All],[Product ID]],Table2[[#All],[Category]])} -> Toys | S57: {=_xlfn.XLOOKUP(Table1[[#This Row],[Customer ID]],Table4[[#All],[Customer ID]],Table4[[#All],[Customer Name]])} -> Emma King | T57: =IF(E57-B57<=2,"Fast","Slow") -> Slow | U57: =IFERROR(IF(E57="","Cancellations",E57),0) -> 45220 | V57: =IF(OR(F57<>"",N57="Cancelled"),"Cancelled","Delivered") -> Delivered | W57: =IF(V57="Cancelled",1,0) -> 0 | X57: =VLOOKUP(H57,ProductMaster!$A$1:$E$23,2,0) -> Leg Set
A58: ORD0057 | B58: 45108 | C58: =TEXT(B58,"mmm") -> Jul | D58: =TEXT(B58,"yyy") -> 2023 | E58: 45170 | G58: CUST025 | H58: PROD005 | I58: Central | J58: 26 | K58: 1 | L58: 26 | M58: Apple Pay | N58: Delivered | O58: DHL | P58: =K58*J58 -> 26 | Q58: =IF(N58="Delivered",E58-B58,"") -> 62 | R58: {=_xlfn.XLOOKUP(Table1[[#This Row],[Product ID]],Table2[[#All],[Product ID]],Table2[[#All],[Category]])} -> Fashion | S58: {=_xlfn.XLOOKUP(Table1[[#This Row],[Customer ID]],Table4[[#All],[Customer ID]],Table4[[#All],[Customer Name]])} -> Emma King | T58: =IF(E58-B58<=2,"Fast","Slow") -> Slow | U58: =IFERROR(IF(E58="","Cancellations",E58),0) -> 45170 | V58: =IF(OR(F58<>"",N58="Cancelled"),"Cancelled","Delivered") -> Delivered | W58: =IF(V58="Cancelled",1,0) -> 0 | X58: =VLOOKUP(H58,ProductMaster!$A$1:$E$23,2,0) -> T-Shirt
A59: ORD0058 | B59: 45143 | C59: =TEXT(B59,"mmm") -> Aug | D59: =TEXT(B59,"yyy") -> 2023 | G59: CUST021 | H59: PROD009 | I59: North | J59: 11 | K59: 5 | L59: 55 | M59: Credit Card | N59: In Transit | O59: FedEx | P59: =K59*J59 -> 55 | Q59: =IF(N59="Delivered",E59-B59,"") | R59: {=_xlfn.XLOOKUP(Table1[[#This Row],[Product ID]],Table2[[#All],[Product ID]],Table2[[#All],[Category]])} -> Books | S59: {=_xlfn.XLOOKUP(Table1[[#This Row],[Customer ID]],Table4[[#All],[Customer ID]],Table4[[#All],[Customer Name]])} -> Zoe Mitchell | T59: =IF(E59-B59<=2,"Fast","Slow") -> Fast | U59: =IFERROR(IF(E59="","Cancellations",E59),0) -> Cancellations | V59: =IF(OR(F59<>"",N59="Cancelled"),"Cancelled","Delivered") -> Delivered | W59: =IF(V59="Cancelled",1,0) -> 0 | X59: =VLOOKUP(H59,ProductMaster!$A$1:$E$23,2,0) -> Magazine
A60: ORD0059 | B60: 44961 | C60: =TEXT(B60,"mmm") -> Feb | D60: =TEXT(B60,"yyy") -> 2023 | F60: 45050 | G60: CUST003 | H60: PROD013 | I60: North | J60: 195 | K60: 4 | L60: 780 | M60: PayPal | N60: Cancelled | O60: FedEx | P60: =K60*J60 -> 780 | Q60: =IF(N60="Delivered",E60-B60,"") | R60: {=_xlfn.XLOOKUP(Table1[[#This Row],[Product ID]],Table2[[#All],[Product ID]],Table2[[#All],[Category]])} -> Home | S60: {=_xlfn.XLOOKUP(Table1[[#This Row],[Customer ID]],Table4[[#All],[Customer ID]],Table4[[#All],[Customer Name]])} -> Ethan Davis | T60: =IF(E60-B60<=2,"Fast","Slow") -> Fast | U60: =IFERROR(IF(E60="","Cancellations",E60),0) -> Cancellations | V60: =IF(OR(F60<>"",N60="Cancelled"),"Cancelled","Delivered") -> Cancelled | W60: =IF(V60="Cancelled",1,0) -> 1 | X60: =VLOOKUP(H60,ProductMaster!$A$1:$E$23,2,0) -> Vacuum Cleaner
A61: ORD0060 | B61: 45240 | C61: =TEXT(B61,"mmm") -> Nov | D61: =TEXT(B61,"yyy") -> 2023 | F61: 45270 | G61: CUST019 | H61: PROD019 | I61: West | J61: 44 | K61: 5 | L61: 220 | M61: Apple Pay | N61: Cancelled | O61: USPS | P61: =K61*J61 -> 220 | Q61: =IF(N61="Delivered",E61-B61,"") | R61: {=_xlfn.XLOOKUP(Table1[[#This Row],[Product ID]],Table2[[#All],[Product ID]],Table2[[#All],[Category]])} -> Fashion | S61: {=_xlfn.XLOOKUP(Table1[[#This Row],[Customer ID]],Table4[[#All],[Customer ID]],Table4[[#All],[Customer Name]])} -> Ava Robinson | T61: =IF(E61-B61<=2,"Fast","Slow") -> Fast | U61: =IFERROR(IF(E61="","Cancellations",E61),0) -> Cancellations | V61: =IF(OR(F61<>"",N61="Cancelled"),"Cancelled","Delivered") -> Cancelled | W61: =IF(V61="Cancelled",1,0) -> 1 | X61: =VLOOKUP(H61,ProductMaster!$A$1:$E$23,2,0) -> Formal Shirt
A62: ORD0061 | B62: 45208 | C62: =TEXT(B62,"mmm") -> Oct | D62: =TEXT(B62,"yyy") -> 2023 | G62: CUST035 | H62: PROD008 | I62: East | J62: 69 | K62: 4 | L62: 276 | M62: Debit Card | N62: In Transit | O62: DHL | P62: =K62*J62 -> 276 | Q62: =IF(N62="Delivered",E62-B62,"") | R62: {=_xlfn.XLOOKUP(Table1[[#This Row],[Product ID]],Table2[[#All],[Product ID]],Table2[[#All],[Category]])} -> Books | S62: {=_xlfn.XLOOKUP(Table1[[#This Row],[Customer ID]],Table4[[#All],[Customer ID]],Table4[[#All],[Customer Name]])} -> Scarlett Adams | T62: =IF(E62-B62<=2,"Fast","Slow") -> Fast | U62: =IFERROR(IF(E62="","Cancellations",E62),0) -> Cancellations | V62: =IF(OR(F62<>"",N62="Cancelled"),"Cancelled","Delivered") -> Delivered | W62: =IF(V62="Cancelled",1,0) -> 0 | X62: =VLOOKUP(H62,ProductMaster!$A$1:$E$23,2,0) -> Textbook
A63: ORD0062 | B63: 45252 | C63: =TEXT(B63,"mmm") -> Nov | D63: =TEXT(B63,"yyy") -> 2023 | E63: 45259 | G63: CUST022 | H63: PROD001 | I63: North | J63: 815 | K63: 4 | L63: 3260 | M63: Credit Card | N63: Delivered | O63: USPS | P63: =K63*J63 -> 3260 | Q63: =IF(N63="Delivered",E63-B63,"") -> 7 | R63: {=_xlfn.XLOOKUP(Table1[[#This Row],[Product ID]],Table2[[#All],[Product ID]],Table2[[#All],[Category]])} -> Electronics | S63: {=_xlfn.XLOOKUP(Table1[[#This Row],[Customer ID]],Table4[[#All],[Customer ID]],Table4[[#All],[Customer Name]])} -> Elijah Lewis | T63: =IF(E63-B63<=2,"Fast","Slow") -> Slow | U63: =IFERROR(IF(E63="","Cancellations",E63),0) -> 45259 | V63: =IF(OR(F63<>"",N63="Cancelled"),"Cancelled","Delivered") -> Delivered | W63: =IF(V63="Cancelled",1,0) -> 0 | X63: =VLOOKUP(H63,ProductMaster!$A$1:$E$23,2,0) -> Smartphone
A64: ORD0063 | B64: 44962 | C64: =TEXT(B64,"mmm") -> Feb | D64: =TEXT(B64,"yyy") -> 2023 | G64: CUST004 | H64: PROD005 | I64: East | J64: 27 | K64: 1 | L64: 27 | M64: Debit Card | N64: In Transit | O64: Amazon Logistics | P64: =K64*J64 -> 27 | Q64: =IF(N64="Delivered",E64-B64,"") | R64: {=_xlfn.XLOOKUP(Table1[[#This Row],[Product ID]],Table2[[#All],[Product ID]],Table2[[#All],[Category]])} -> Fashion | S64: {=_xlfn.XLOOKUP(Table1[[#This Row],[Customer ID]],Table4[[#All],[Customer ID]],Table4[[#All],[Customer Name]])} -> Noah Wilson | T64: =IF(E64-B64<=2,"Fast","Slow") -> Fast | U64: =IFERROR(IF(E64="","Cancellations",E64),0) -> Cancellations | V64: =IF(OR(F64<>"",N64="Cancelled"),"Cancelled","Delivered") -> Delivered | W64: =IF(V64="Cancelled",1,0) -> 0 | X64: =VLOOKUP(H64,ProductMaster!$A$1:$E$23,2,0) -> T-Shirt
A65: ORD0064 | B65: 45285 | C65: =TEXT(B65,"mmm") -> Dec | D65: =TEXT(B65,"yyy") -> 2023 | E65: 45289 | G65: CUST048 | H65: PROD003 | I65: West | J65: 139 | K65: 5 | L65: 695 | M65: Apple Pay | N65: Delivered | O65: USPS | P65: =K65*J65 -> 695 | Q65: =IF(N65="Delivered",E65-B65,"") -> 4 | R65: {=_xlfn.XLOOKUP(Table1[[#This Row],[Product ID]],Table2[[#All],[Product ID]],Table2[[#All],[Category]])} -> Home | S65: {=_xlfn.XLOOKUP(Table1[[#This Row],[Customer ID]],Table4[[#All],[Customer ID]],Table4[[#All],[Customer Name]])} -> Noah Wilson | T65: =IF(E65-B65<=2,"Fast","Slow") -> Slow | U65: =IFERROR(IF(E65="","Cancellations",E65),0) -> 45289 | V65: =IF(OR(F65<>"",N65="Cancelled"),"Cancelled","Delivered") -> Delivered | W65: =IF(V65="Cancelled",1,0) -> 0 | X65: =VLOOKUP(H65,ProductMaster!$A$1:$E$23,2,0) -> Cookware Set
A66: ORD0065 | B66: 45217 | C66: =TEXT(B66,"mmm") -> Oct | D66: =TEXT(B66,"yyy") -> 2023 | F66: 45219 | G66: CUST009 | H66: PROD008 | I66: South | J66: 69 | K66: 3 | L66: 207 | M66: PayPal | N66: Cancelled | O66: Amazon Logistics | P66: =K66*J66 -> 207 | Q66: =IF(N66="Delivered",E66-B66,"") | R66: {=_xlfn.XLOOKUP(Table1[[#This Row],[Product ID]],Table2[[#All],[Product ID]],Table2[[#All],[Category]])} -> Books | S66: {=_xlfn.XLOOKUP(Table1[[#This Row],[Customer ID]],Table4[[#All],[Customer ID]],Table4[[#All],[Customer Name]])} -> Jackson Allen | T66: =IF(E66-B66<=2,"Fast","Slow") -> Fast | U66: =IFERROR(IF(E66="","Cancellations",E66),0) -> Cancellations | V66: =IF(OR(F66<>"",N66="Cancelled"),"Cancelled","Delivered") -> Cancelled | W66: =IF(V66="Cancelled",1,0) -> 1 | X66: =VLOOKUP(H66,ProductMaster!$A$1:$E$23,2,0) -> Textbook
A67: ORD0066 | B67: 45066 | C67: =TEXT(B67,"mmm") -> May | D67: =TEXT(B67,"yyy") -> 2023 | F67: 45067 | G67: CUST009 | H67: PROD019 | I67: West | J67: 42 | K67: 1 | L67: 42 | M67: Apple Pay | N67: Cancelled | O67: DHL | P67: =K67*J67 -> 42 | Q67: =IF(N67="Delivered",E67-B67,"") | R67: {=_xlfn.XLOOKUP(Table1[[#This Row],[Product ID]],Table2[[#All],[Product ID]],Table2[[#All],[Category]])} -> Fashion | S67: {=_xlfn.XLOOKUP(Table1[[#This Row],[Customer ID]],Table4[[#All],[Customer ID]],Table4[[#All],[Customer Name]])} -> Jackson Allen | T67: =IF(E67-B67<=2,"Fast","Slow") -> Fast | U67: =IFERROR(IF(E67="","Cancellations",E67),0) -> Cancellations | V67: =IF(OR(F67<>"",N67="Cancelled"),"Cancelled","Delivered") -> Cancelled | W67: =IF(V67="Cancelled",1,0) -> 1 | X67: =VLOOKUP(H67,ProductMaster!$A$1:$E$23,2,0) -> Formal Shirt
A68: ORD0067 | B68: 45135 | C68: =TEXT(B68,"mmm") -> Jul | D68: =TEXT(B68,"yyy") -> 2023 | E68: 45137 | G68: CUST050 | H68: PROD007 | I68: North | J68: 31 | K68: 4 | L68: 124 | M68: Credit Card | N68: Delivered | O68: UPS | P68: =K68*J68 -> 124 | Q68: =IF(N68="Delivered",E68-B68,"") -> 2 | R68: {=_xlfn.XLOOKUP(Table1[[#This Row],[Product ID]],Table2[[#All],[Product ID]],Table2[[#All],[Category]])} -> Toys | S68: {=_xlfn.XLOOKUP(Table1[[#This Row],[Customer ID]],Table4[[#All],[Customer ID]],Table4[[#All],[Customer Name]])} -> #N/A | T68: =IF(E68-B68<=2,"Fast","Slow") -> Fast | U68: =IFERROR(IF(E68="","Cancellations",E68),0) -> 45137 | V68: =IF(OR(F68<>"",N68="Cancelled"),"Cancelled","Delivered") -> Delivered | W68: =IF(V68="Cancelled",1,0) -> 0 | X68: =VLOOKUP(H68,ProductMaster!$A$1:$E$23,2,0) -> Puzzle
A69: ORD0068 | B69: 45278 | C69: =TEXT(B69,"mmm") -> Dec | D69: =TEXT(B69,"yyy") -> 2023 | G69: CUST045 | H69: PROD020 | I69: West | J69: 104 | K69: 3 | L69: 312 | M69: Credit Card | N69: In Transit | O69: UPS | P69: =K69*J69 -> 312 | Q69: =IF(N69="Delivered",E69-B69,"") | R69: {=_xlfn.XLOOKUP(Table1[[#This Row],[Product ID]],Table2[[#All],[Product ID]],Table2[[#All],[Category]])} -> Electronics | S69: {=_xlfn.XLOOKUP(Table1[[#This Row],[Customer ID]],Table4[[#All],[Customer ID]],Table4[[#All],[Customer Name]])} -> Emily Johnson | T69: =IF(E69-B69<=2,"Fast","Slow") -> Fast | U69: =IFERROR(IF(E69="","Cancellations",E69),0) -> Cancellations | V69: =IF(OR(F69<>"",N69="Cancelled"),"Cancelled","Delivered") -> Delivered | W69: =IF(V69="Cancelled",1,0) -> 0 | X69: =VLOOKUP(H69,ProductMaster!$A$1:$E$23,2,0) -> Bluetooth Speaker
A70: ORD0069 | B70: 44964 | C70: =TEXT(B70,"mmm") -> Feb | D70: =TEXT(B70,"yyy") -> 2023 | F70: 45114 | G70: CUST044 | H70: PROD010 | I70: East | J70: 58 | K70: 2 | L70: 116 | M70: Apple Pay | N70: Cancelled | O70: USPS | P70: =K70*J70 -> 116 | Q70: =IF(N70="Delivered",E70-B70,"") | R70: {=_xlfn.XLOOKUP(Table1[[#This Row],[Product ID]],Table2[[#All],[Product ID]],Table2[[#All],[Category]])} -> Fashion | S70: {=_xlfn.XLOOKUP(Table1[[#This Row],[Customer ID]],Table4[[#All],[Customer ID]],Table4[[#All],[Customer Name]])} -> Grace Ward | T70: =IF(E70-B70<=2,"Fast","Slow") -> Fast | U70: =IFERROR(IF(E70="","Cancellations",E70),0) -> Cancellations | V70: =IF(OR(F70<>"",N70="Cancelled"),"Cancelled","Delivered") -> Cancelled | W70: =IF(V70="Cancelled",1,0) -> 1 | X70: =VLOOKUP(H70,ProductMaster!$A$1:$E$23,2,0) -> Jeans
A71: ORD0070 | B71: 45179 | C71: =TEXT(B71,"mmm") -> Sep | D71: =TEXT(B71,"yyy") -> 2023 | F71: 45209 | G71: CUST009 | H71: PROD004 | I71: West | J71: 62 | K71: 2 | L71: 124 | M71: Debit Card | N71: Cancelled | O71: DHL | P71: =K71*J71 -> 124 | Q71: =IF(N71="Delivered",E71-B71,"") | R71: {=_xlfn.XLOOKUP(Table1[[#This Row],[Product ID]],Table2[[#All],[Product ID]],Table2[[#All],[Category]])} -> Toys | S71: {=_xlfn.XLOOKUP(Table1[[#This Row],[Customer ID]],Table4[[#All],[Customer ID]],Table4[[#All],[Customer Name]])} -> Jackson Allen | T71: =IF(E71-B71<=2,"Fast","Slow") -> Fast | U71: =IFERROR(IF(E71="","Cancellations",E71),0) -> Cancellations | V71: =IF(OR(F71<>"",N71="Cancelled"),"Cancelled","Delivered") -> Cancelled | W71: =IF(V71="Cancelled",1,0) -> 1 | X71: =VLOOKUP(H71,ProductMaster!$A$1:$E$23,2,0) -> Leg Set
A72: ORD0071 | B72: 45278 | C72: =TEXT(B72,"mmm") -> Dec | D72: =TEXT(B72,"yyy") -> 2023 | E72: 45285 | G72: CUST006 | H72: PROD019 | I72: East | J72: 43 | K72: 1 | L72: 43 | M72: Credit Card | N72: Delivered | O72: Amazon Logistics | P72: =K72*J72 -> 43 | Q72: =IF(N72="Delivered",E72-B72,"") -> 7 | R72: {=_xlfn.XLOOKUP(Table1[[#This Row],[Product ID]],Table2[[#All],[Product ID]],Table2[[#All],[Category]])} -> Fashion | S72: {=_xlfn.XLOOKUP(Table1[[#This Row],[Customer ID]],Table4[[#All],[Customer ID]],Table4[[#All],[Customer Name]])} -> Ava Robinson | T72: =IF(E72-B72<=2,"Fast","Slow") -> Slow | U72: =IFERROR(IF(E72="","Cancellations",E72),0) -> 45285 | V72: =IF(OR(F72<>"",N72="Cancelled"),"Cancelled","Delivered") -> Delivered | W72: =IF(V72="Cancelled",1,0) -> 0 | X72: =VLOOKUP(H72,ProductMaster!$A$1:$E$23,2,0) -> Formal Shirt
A73: ORD0072 | B73: 45110 | C73: =TEXT(B73,"mmm") -> Jul | D73: =TEXT(B73,"yyy") -> 2023 | G73: CUST022 | H73: PROD004 | I73: East | J73: 62 | K73: 4 | L73: 248 | M73: Debit Card | N73: In Transit | O73: Amazon Logistics | P73: =K73*J73 -> 248 | Q73: =IF(N73="Delivered",E73-B73,"") | R73: {=_xlfn.XLOOKUP(Table1[[#This Row],[Product ID]],Table2[[#All],[Product ID]],Table2[[#All],[Category]])} -> Toys | S73: {=_xlfn.XLOOKUP(Table1[[#This Row],[Customer ID]],Table4[[#All],[Customer ID]],Table4[[#All],[Customer Name]])} -> Elijah Lewis | T73: =IF(E73-B73<=2,"Fast","Slow") -> Fast | U73: =IFERROR(IF(E73="","Cancellations",E73),0) -> Cancellations | V73: =IF(OR(F73<>"",N73="Cancelled"),"Cancelled","Delivered") -> Delivered | W73: =IF(V73="Cancelled",1,0) -> 0 | X73: =VLOOKUP(H73,ProductMaster!$A$1:$E$23,2,0) -> Leg Set
A74: ORD0073 | B74: 45129 | C74: =TEXT(B74,"mmm") -> Jul | D74: =TEXT(B74,"yyy") -> 2023 | F74: 44982 | G74: CUST028 | H74: PROD006 | I74: North | J74: 95 | K74: 2 | L74: 190 | M74: PayPal | N74: Cancelled | O74: UPS | P74: =K74*J74 -> 190 | Q74: =IF(N74="Delivered",E74-B74,"") | R74: {=_xlfn.XLOOKUP(Table1[[#This Row],[Product ID]],Table2[[#All],[Product ID]],Table2[[#All],[Category]])} -> Fashion | S74: {=_xlfn.XLOOKUP(Table1[[#This Row],[Customer ID]],Table4[[#All],[Customer ID]],Table4[[#All],[Customer Name]])} -> Lily Bennett | T74: =IF(E74-B74<=2,"Fast","Slow") -> Fast | U74: =IFERROR(IF(E74="","Cancellations",E74),0) -> Cancellations | V74: =IF(OR(F74<>"",N74="Cancelled"),"Cancelled","Delivered") -> Cancelled | W74: =IF(V74="Cancelled",1,0) -> 1 | X74: =VLOOKUP(H74,ProductMaster!$A$1:$E$23,2,0) -> Shoes
A75: ORD0074 | B75: 44944 | C75: =TEXT(B75,"mmm") -> Jan | D75: =TEXT(B75,"yyy") -> 2023 | E75: 44950 | G75: CUST016 | H75: PROD021 | I75: Central | J75: 36 | K75: 4 | L75: 144 | M75: Apple Pay | N75: Delivered | O75: FedEx | P75: =K75*J75 -> 144 | Q75: =IF(N75="Delivered",E75-B75,"") -> 6 | R75: {=_xlfn.XLOOKUP(Table1[[#This Row],[Product ID]],Table2[[#All],[Product ID]],Table2[[#All],[Category]])} -> Home | S75: {=_xlfn.XLOOKUP(Table1[[#This Row],[Customer ID]],Table4[[#All],[Customer ID]],Table4[[#All],[Customer Name]])} -> Elijah Lewis | T75: =IF(E75-B75<=2,"Fast","Slow") -> Slow | U75: =IFERROR(IF(E75="","Cancellations",E75),0) -> 44950 | V75: =IF(OR(F75<>"",N75="Cancelled"),"Cancelled","Delivered") -> Delivered | W75: =IF(V75="Cancelled",1,0) -> 0 | X75: =VLOOKUP(H75,ProductMaster!$A$1:$E$23,2,0) -> Wall Clock
A76: ORD0075 | B76: 45070 | C76: =TEXT(B76,"mmm") -> May | D76: =TEXT(B76,"yyy") -> 2023 | G76: CUST042 | H76: PROD017 | I76: East | J76: 73 | K76: 5 | L76: 365 | M76: Apple Pay | N76: In Transit | O76: DHL | P76: =K76*J76 -> 365 | Q76: =IF(N76="Delivered",E76-B76,"") | R76: {=_xlfn.XLOOKUP(Table1[[#This Row],[Product ID]],Table2[[#All],[Product ID]],Table2[[#All],[Category]])} -> Electronics | S76: {=_xlfn.XLOOKUP(Table1[[#This Row],[Customer ID]],Table4[[#All],[Customer ID]],Table4[[#All],[Customer Name]])} -> Noah Wilson | T76: =IF(E76-B76<=2,"Fast","Slow") -> Fast | U76: =IFERROR(IF(E76="","Cancellations",E76),0) -> Cancellations | V76: =IF(OR(F76<>"",N76="Cancelled"),"Cancelled","Delivered") -> Delivered | W76: =IF(V76="Cancelled",1,0) -> 0 | X76: =VLOOKUP(H76,ProductMaster!$A$1:$E$23,2,0) -> Gaming Mouse
A77: ORD0076 | B77: 44994 | C77: =TEXT(B77,"mmm") -> Mar | D77: =TEXT(B77,"yyy") -> 2023 | E77: 45178 | G77: CUST023 | H77: PROD019 | I77: North | J77: 43 | K77: 4 | L77: 172 | M77: Debit Card | N77: Delivered | O77: DHL | P77: =K77*J77 -> 172 | Q77: =IF(N77="Delivered",E77-B77,"") -> 184 | R77: {=_xlfn.XLOOKUP(Table1[[#This Row],[Product ID]],Table2[[#All],[Product ID]],Table2[[#All],[Category]])} -> Fashion | S77: {=_xlfn.XLOOKUP(Table1[[#This Row],[Customer ID]],Table4[[#All],[Customer ID]],Table4[[#All],[Customer Name]])} -> Charlotte Reed | T77: =IF(E77-B77<=2,"Fast","Slow") -> Slow | U77: =IFERROR(IF(E77="","Cancellations",E77),0) -> 45178 | V77: =IF(OR(F77<>"",N77="Cancelled"),"Cancelled","Delivered") -> Delivered | W77: =IF(V77="Cancelled",1,0) -> 0 | X77: =VLOOKUP(H77,ProductMaster!$A$1:$E$23,2,0) -> Formal Shirt
A78: ORD0077 | B78: 44968 | C78: =TEXT(B78,"mmm") -> Feb | D78: =TEXT(B78,"yyy") -> 2023 | E78: 45027 | G78: CUST004 | H78: PROD016 | I78: West | J78: 214 | K78: 5 | L78: 1070 | M78: Debit Card | N78: Delivered | O78: UPS | P78: =K78*J78 -> 1070 | Q78: =IF(N78="Delivered",E78-B78,"") -> 59 | R78: {=_xlfn.XLOOKUP(Table1[[#This Row],[Product ID]],Table2[[#All],[Product ID]],Table2[[#All],[Category]])} -> Home | S78: {=_xlfn.XLOOKUP(Table1[[#This Row],[Customer ID]],Table4[[#All],[Customer ID]],Table4[[#All],[Customer Name]])} -> Noah Wilson | T78: =IF(E78-B78<=2,"Fast","Slow") -> Slow | U78: =IFERROR(IF(E78="","Cancellations",E78),0) -> 45027 | V78: =IF(OR(F78<>"",N78="Cancelled"),"Cancelled","Delivered") -> Delivered | W78: =IF(V78="Cancelled",1,0) -> 0 | X78: =VLOOKUP(H78,ProductMaster!$A$1:$E$23,2,0) -> Cookware Set Pro
A79: ORD0078 | B79: 44997 | C79: =TEXT(B79,"mmm") -> Mar | D79: =TEXT(B79,"yyy") -> 2023 | F79: 45089 | G79: CUST048 | H79: PROD002 | I79: Central | J79: 42 | K79: 2 | L79: 84 | M79: Apple Pay | N79: Cancelled | O79: UPS | P79: =K79*J79 -> 84 | Q79: =IF(N79="Delivered",E79-B79,"") | R79: {=_xlfn.XLOOKUP(Table1[[#This Row],[Product ID]],Table2[[#All],[Product ID]],Table2[[#All],[Category]])} -> Toys | S79: {=_xlfn.XLOOKUP(Table1[[#This Row],[Customer ID]],Table4[[#All],[Customer ID]],Table4[[#All],[Customer Name]])} -> Noah Wilson | T79: =IF(E79-B79<=2,"Fast","Slow") -> Fast | U79: =IFERROR(IF(E79="","Cancellations",E79),0) -> Cancellations | V79: =IF(OR(F79<>"",N79="Cancelled"),"Cancelled","Delivered") -> Cancelled | W79: =IF(V79="Cancelled",1,0) -> 1 | X79: =VLOOKUP(H79,ProductMaster!$A$1:$E$23,2,0) -> Action Figure
A80: ORD0079 | B80: 44930 | C80: =TEXT(B80,"mmm") -> Jan | D80: =TEXT(B80,"yyy") -> 2023 | G80: CUST048 | H80: PROD012 | I80: North | J80: 46 | K80: 1 | L80: 46 | M80: Amazon Pay | N80: In Transit | O80: UPS | P80: =K80*J80 -> 46 | Q80: =IF(N80="Delivered",E80-B80,"") | R80: {=_xlfn.XLOOKUP(Table1[[#This Row],[Product ID]],Table2[[#All],[Product ID]],Table2[[#All],[Category]])} -> Home | S80: {=_xlfn.XLOOKUP(Table1[[#This Row],[Customer ID]],Table4[[#All],[Customer ID]],Table4[[#All],[Customer Name]])} -> Noah Wilson | T80: =IF(E80-B80<=2,"Fast","Slow") -> Fast | U80: =IFERROR(IF(E80="","Cancellations",E80),0) -> Cancellations | V80: =IF(OR(F80<>"",N80="Cancelled"),"Cancelled","Delivered") -> Delivered | W80: =IF(V80="Cancelled",1,0) -> 0 | X80: =VLOOKUP(H80,ProductMaster!$A$1:$E$23,2,0) -> Lamp
A81: ORD0080 | B81: 45215 | C81: =TEXT(B81,"mmm") -> Oct | D81: =TEXT(B81,"yyy") -> 2023 | E81: 45218 | G81: CUST032 | H81: PROD018 | I81: East | J81: 95 | K81: 4 | L81: 380 | M81: Credit Card | N81: Delivered | O81: UPS | P81: =K81*J81 -> 380 | Q81: =IF(N81="Delivered",E81-B81,"") -> 3 | R81: {=_xlfn.XLOOKUP(Table1[[#This Row],[Product ID]],Table2[[#All],[Product ID]],Table2[[#All],[Category]])} -> Toys | S81: {=_xlfn.XLOOKUP(Table1[[#This Row],[Customer ID]],Table4[[#All],[Customer ID]],Table4[[#All],[Customer Name]])} -> Luke Gray | T81: =IF(E81-B81<=2,"Fast","Slow") -> Slow | U81: =IFERROR(IF(E81="","Cancellations",E81),0) -> 45218 | V81: =IF(OR(F81<>"",N81="Cancelled"),"Cancelled","Delivered") -> Delivered | W81: =IF(V81="Cancelled",1,0) -> 0 | X81: =VLOOKUP(H81,ProductMaster!$A$1:$E$23,2,0) -> Doll House
A82: ORD0081 | B82: 45057 | C82: =TEXT(B82,"mmm") -> May | D82: =TEXT(B82,"yyy") -> 2023 | G82: CUST001 | H82: PROD011 | I82: West | J82: 174 | K82: 2 | L82: 348 | M82: PayPal | N82: In Transit | O82: UPS | P82: =K82*J82 -> 348 | Q82: =IF(N82="Delivered",E82-B82,"") | R82: {=_xlfn.XLOOKUP(Table1[[#This Row],[Product ID]],Table2[[#All],[Product ID]],Table2[[#All],[Category]])} -> Electronics | S82: {=_xlfn.XLOOKUP(Table1[[#This Row],[Customer ID]],Table4[[#All],[Customer ID]],Table4[[#All],[Customer Name]])} -> James Miller | T82: =IF(E82-B82<=2,"Fast","Slow") -> Fast | U82: =IFERROR(IF(E82="","Cancellations",E82),0) -> Cancellations | V82: =IF(OR(F82<>"",N82="Cancelled"),"Cancelled","Delivered") -> Delivered | W82: =IF(V82="Cancelled",1,0) -> 0 | X82: =VLOOKUP(H82,ProductMaster!$A$1:$E$23,2,0) -> Headphones
A83: ORD0082 | B83: 45092 | C83: =TEXT(B83,"mmm") -> Jun | D83: =TEXT(B83,"yyy") -> 2023 | F83: 45095 | G83: CUST046 | H83: PROD005 | I83: North | J83: 27 | K83: 5 | L83: 135 | M83: Credit Card | N83: Cancelled | O83: Amazon Logistics | P83: =K83*J83 -> 135 | Q83: =IF(N83="Delivered",E83-B83,"") | R83: {=_xlfn.XLOOKUP(Table1[[#This Row],[Product ID]],Table2[[#All],[Product ID]],Table2[[#All],[Category]])} -> Fashion | S83: {=_xlfn.XLOOKUP(Table1[[#This Row],[Customer ID]],Table4[[#All],[Customer ID]],Table4[[#All],[Customer Name]])} -> Emily Johnson | T83: =IF(E83-B83<=2,"Fast","Slow") -> Fast | U83: =IFERROR(IF(E83="","Cancellations",E83),0) -> Cancellations | V83: =IF(OR(F83<>"",N83="Cancelled"),"Cancelled","Delivered") -> Cancelled | W83: =IF(V83="Cancelled",1,0) -> 1 | X83: =VLOOKUP(H83,ProductMaster!$A$1:$E$23,2,0) -> T-Shirt
A84: ORD0083 | B84: 45227 | C84: =TEXT(B84,"mmm") -> Oct | D84: =TEXT(B84,"yyy") -> 2023 | E84: 45229 | G84: CUST021 | H84: PROD005 | I84: South | J84: 27 | K84: 4 | L84: 108 | M84: PayPal | N84: Delivered | O84: USPS | P84: =K84*J84 -> 108 | Q84: =IF(N84="Delivered",E84-B84,"") -> 2 | R84: {=_xlfn.XLOOKUP(Table1[[#This Row],[Product ID]],Table2[[#All],[Product ID]],Table2[[#All],[Category]])} -> Fashion | S84: {=_xlfn.XLOOKUP(Table1[[#This Row],[Customer ID]],Table4[[#All],[Customer ID]],Table4[[#All],[Customer Name]])} -> Zoe Mitchell | T84: =IF(E84-B84<=2,"Fast","Slow") -> Fast | U84: =IFERROR(IF(E84="","Cancellations",E84),0) -> 45229 | V84: =IF(OR(F84<>"",N84="Cancelled"),"Cancelled","Delivered") -> Delivered | W84: =IF(V84="Cancelled",1,0) -> 0 | X84: =VLOOKUP(H84,ProductMaster!$A$1:$E$23,2,0) -> T-Shirt
A85: ORD0084 | B85: 45282 | C85: =TEXT(B85,"mmm") -> Dec | D85: =TEXT(B85,"yyy") -> 2023 | G85: CUST015 | H85: PROD022 | I85: South | J85: 65 | K85: 2 | L85: 130 | M85: PayPal | N85: In Transit | O85: DHL | P85: =K85*J85 -> 130 | Q85: =IF(N85="Delivered",E85-B85,"") | R85: {=_xlfn.XLOOKUP(Table1[[#This Row],[Product ID]],Table2[[#All],[Product ID]],Table2[[#All],[Category]])} -> Fashion | S85: {=_xlfn.XLOOKUP(Table1[[#This Row],[Customer ID]],Table4[[#All],[Customer ID]],Table4[[#All],[Customer Name]])} -> Ava White | T85: =IF(E85-B85<=2,"Fast","Slow") -> Fast | U85: =IFERROR(IF(E85="","Cancellations",E85),0) -> Cancellations | V85: =IF(OR(F85<>"",N85="Cancelled"),"Cancelled","Delivered") -> Delivered | W85: =IF(V85="Cancelled",1,0) -> 0 | X85: =VLOOKUP(H85,ProductMaster!$A$1:$E$23,2,0) -> Backpack
A86: ORD0085 | B86: 45110 | C86: =TEXT(B86,"mmm") -> Jul | D86: =TEXT(B86,"yyy") -> 2023 | G86: CUST045 | H86: PROD019 | I86: East | J86: 43 | K86: 5 | L86: 215 | M86: Debit Card | N86: In Transit | O86: DHL | P86: =K86*J86 -> 215 | Q86: =IF(N86="Delivered",E86-B86,"") | R86: {=_xlfn.XLOOKUP(Table1[[#This Row],[Product ID]],Table2[[#All],[Product ID]],Table2[[#All],[Category]])} -> Fashion | S86: {=_xlfn.XLOOKUP(Table1[[#This Row],[Customer ID]],Table4[[#All],[Customer ID]],Table4[[#All],[Customer Name]])} -> Emily Johnson | T86: =IF(E86-B86<=2,"Fast","Slow") -> Fast | U86: =IFERROR(IF(E86="","Cancellations",E86),0) -> Cancellations | V86: =IF(OR(F86<>"",N86="Cancelled"),"Cancelled","Delivered") -> Delivered | W86: =IF(V86="Cancelled",1,0) -> 0 | X86: =VLOOKUP(H86,ProductMaster!$A$1:$E$23,2,0) -> Formal Shirt
A87: ORD0086 | B87: 45210 | C87: =TEXT(B87,"mmm") -> Oct | D87: =TEXT(B87,"yyy") -> 2023 | G87: CUST007 | H87: PROD016 | I87: West | J87: 210 | K87: 1 | L87: 210 | M87: PayPal | N87: In Transit | O87: UPS | P87: =K87*J87 -> 210 | Q87: =IF(N87="Delivered",E87-B87,"") | R87: {=_xlfn.XLOOKUP(Table1[[#This Row],[Product ID]],Table2[[#All],[Product ID]],Table2[[#All],[Category]])} -> Home | S87: {=_xlfn.XLOOKUP(Table1[[#This Row],[Customer ID]],Table4[[#All],[Customer ID]],Table4[[#All],[Customer Name]])} -> Liam Walker | T87: =IF(E87-B87<=2,"Fast","Slow") -> Fast | U87: =IFERROR(IF(E87="","Cancellations",E87),0) -> Cancellations | V87: =IF(OR(F87<>"",N87="Cancelled"),"Cancelled","Delivered") -> Delivered | W87: =IF(V87="Cancelled",1,0) -> 0 | X87: =VLOOKUP(H87,ProductMaster!$A$1:$E$23,2,0) -> Cookware Set Pro
A88: ORD0087 | B88: 45252 | C88: =TEXT(B88,"mmm") -> Nov | D88: =TEXT(B88,"yyy") -> 2023 | G88: CUST043 | H88: PROD021 | I88: South | J88: 37 | K88: 3 | L88: 111 | M88: Credit Card | N88: In Transit | O88: UPS | P88: =K88*J88 -> 111 | Q88: =IF(N88="Delivered",E88-B88,"") | R88: {=_xlfn.XLOOKUP(Table1[[#This Row],[Product ID]],Table2[[#All],[Product ID]],Table2[[#All],[Category]])} -> Home | S88: {=_xlfn.XLOOKUP(Table1[[#This Row],[Customer ID]],Table4[[#All],[Customer ID]],Table4[[#All],[Customer Name]])} -> Lily Reed | T88: =IF(E88-B88<=2,"Fast","Slow") -> Fast | U88: =IFERROR(IF(E88="","Cancellations",E88),0) -> Cancellations | V88: =IF(OR(F88<>"",N88="Cancelled"),"Cancelled","Delivered") -> Delivered | W88: =IF(V88="Cancelled",1,0) -> 0 | X88: =VLOOKUP(H88,ProductMaster!$A$1:$E$23,2,0) -> Wall Clock
A89: ORD0088 | B89: 45143 | C89: =TEXT(B89,"mmm") -> Aug | D89: =TEXT(B89,"yyy") -> 2023 | G89: CUST007 | H89: PROD001 | I89: South | J89: 788 | K89: 4 | L89: 3152 | M89: Debit Card | N89: In Transit | O89: Amazon Logistics | P89: =K89*J89 -> 3152 | Q89: =IF(N89="Delivered",E89-B89,"") | R89: {=_xlfn.XLOOKUP(Table1[[#This Row],[Product ID]],Table2[[#All],[Product ID]],Table2[[#All],[Category]])} -> Electronics | S89: {=_xlfn.XLOOKUP(Table1[[#This Row],[Customer ID]],Table4[[#All],[Customer ID]],Table4[[#All],[Customer Name]])} -> Liam Walker | T89: =IF(E89-B89<=2,"Fast","Slow") -> Fast | U89: =IFERROR(IF(E89="","Cancellations",E89),0) -> Cancellations | V89: =IF(OR(F89<>"",N89="Cancelled"),"Cancelled","Delivered") -> Delivered | W89: =IF(V89="Cancelled",1,0) -> 0 | X89: =VLOOKUP(H89,ProductMaster!$A$1:$E$23,2,0) -> Smartphone
A90: ORD0089 | B90: 45120 | C90: =TEXT(B90,"mmm") -> Jul | D90: =TEXT(B90,"yyy") -> 2023 | G90: CUST007 | H90: PROD016 | I90: West | J90: 217 | K90: 5 | L90: 1085 | M90: Debit Card | N90: In Transit | O90: FedEx | P90: =K90*J90 -> 1085 | Q90: =IF(N90="Delivered",E90-B90,"") | R90: {=_xlfn.XLOOKUP(Table1[[#This Row],[Product ID]],Table2[[#All],[Product ID]],Table2[[#All],[Category]])} -> Home | S90: {=_xlfn.XLOOKUP(Table1[[#This Row],[Customer ID]],Table4[[#All],[Customer ID]],Table4[[#All],[Customer Name]])} -> Liam Walker | T90: =IF(E90-B90<=2,"Fast","Slow") -> Fast | U90: =IFERROR(IF(E90="","Cancellations",E90),0) -> Cancellations | V90: =IF(OR(F90<>"",N90="Cancelled"),"Cancelled","Delivered") -> Delivered | W90: =IF(V90="Cancelled",1,0) -> 0 | X90: =VLOOKUP(H90,ProductMaster!$A$1:$E$23,2,0) -> Cookware Set Pro
A91: ORD0090 | B91: 44944 | C91: =TEXT(B91,"mmm") -> Jan | D91: =TEXT(B91,"yyy") -> 2023 | G91: CUST007 | H91: PROD003 | I91: West | J91: 138 | K91: 4 | L91: 552 | M91: Credit Card | N91: In Transit | O91: FedEx | P91: =K91*J91 -> 552 | Q91: =IF(N91="Delivered",E91-B91,"") | R91: {=_xlfn.XLOOKUP(Table1[[#This Row],[Product ID]],Table2[[#All],[Product ID]],Table2[[#All],[Category]])} -> Home | S91: {=_xlfn.XLOOKUP(Table1[[#This Row],[Customer ID]],Table4[[#All],[Customer ID]],Table4[[#All],[Customer Name]])} -> Liam Walker | T91: =IF(E91-B91<=2,"Fast","Slow") -> Fast | U91: =IFERROR(IF(E91="","Cancellations",E91),0) -> Cancellations | V91: =IF(OR(F91<>"",N91="Cancelled"),"Cancelled","Delivered") -> Delivered | W91: =IF(V91="Cancelled",1,0) -> 0 | X91: =VLOOKUP(H91,ProductMaster!$A$1:$E$23,2,0) -> Cookware Set
A92: ORD0091 | B92: 45100 | C92: =TEXT(B92,"mmm") -> Jun | D92: =TEXT(B92,"yyy") -> 2023 | E92: 45106 | G92: CUST031 | H92: PROD001 | I92: Central | J92: 803 | K92: 2 | L92: 1606 | M92: Apple Pay | N92: Delivered | O92: FedEx | P92: =K92*J92 -> 1606 | Q92: =IF(N92="Delivered",E92-B92,"") -> 6 | R92: {=_xlfn.XLOOKUP(Table1[[#This Row],[Product ID]],Table2[[#All],[Product ID]],Table2[[#All],[Category]])} -> Electronics | S92: {=_xlfn.XLOOKUP(Table1[[#This Row],[Customer ID]],Table4[[#All],[Customer ID]],Table4[[#All],[Customer Name]])} -> Mason Collins | T92: =IF(E92-B92<=2,"Fast","Slow") -> Slow | U92: =IFERROR(IF(E92="","Cancellations",E92),0) -> 45106 | V92: =IF(OR(F92<>"",N92="Cancelled"),"Cancelled","Delivered") -> Delivered | W92: =IF(V92="Cancelled",1,0) -> 0 | X92: =VLOOKUP(H92,ProductMaster!$A$1:$E$23,2,0) -> Smartphone
A93: ORD0092 | B93: 44978 | C93: =TEXT(B93,"mmm") -> Feb | D93: =TEXT(B93,"yyy") -> 2023 | F93: 44982 | G93: CUST013 | H93: PROD014 | I93: North | J93: 248 | K93: 5 | L93: 1240 | M93: PayPal | N93: Cancelled | O93: UPS | P93: =K93*J93 -> 1240 | Q93: =IF(N93="Delivered",E93-B93,"") | R93: {=_xlfn.XLOOKUP(Table1[[#This Row],[Product ID]],Table2[[#All],[Product ID]],Table2[[#All],[Category]])} -> Electronics | S93: {=_xlfn.XLOOKUP(Table1[[#This Row],[Customer ID]],Table4[[#All],[Customer ID]],Table4[[#All],[Customer Name]])} -> Olivia Martinez | T93: =IF(E93-B93<=2,"Fast","Slow") -> Fast | U93: =IFERROR(IF(E93="","Cancellations",E93),0) -> Cancellations | V93: =IF(OR(F93<>"",N93="Cancelled"),"Cancelled","Delivered") -> Cancelled | W93: =IF(V93="Cancelled",1,0) -> 1 | X93: =VLOOKUP(H93,ProductMaster!$A$1:$E$23,2,0) -> Smartwatch
A94: ORD0093 | B94: 44976 | C94: =TEXT(B94,"mmm") -> Feb | D94: =TEXT(B94,"yyy") -> 2023 | E94: 44978 | G94: CUST036 | H94: PROD016 | I94: East | J94: 210 | K94: 3 | L94: 630 | M94: Apple Pay | N94: Delivered | O94: DHL | P94: =K94*J94 -> 630 | Q94: =IF(N94="Delivered",E94-B94,"") -> 2 | R94: {=_xlfn.XLOOKUP(Table1[[#This Row],[Product ID]],Table2[[#All],[Product ID]],Table2[[#All],[Category]])} -> Home | S94: {=_xlfn.XLOOKUP(Table1[[#This Row],[Customer ID]],Table4[[#All],[Customer ID]],Table4[[#All],[Customer Name]])} -> Ethan Davis | T94: =IF(E94-B94<=2,"Fast","Slow") -> Fast | U94: =IFERROR(IF(E94="","Cancellations",E94),0) -> 44978 | V94: =IF(OR(F94<>"",N94="Cancelled"),"Cancelled","Delivered") -> Delivered | W94: =IF(V94="Cancelled",1,0) -> 0 | X94: =VLOOKUP(H94,ProductMaster!$A$1:$E$23,2,0) -> Cookware Set Pro
A95: ORD0094 | B95: 45058 | C95: =TEXT(B95,"mmm") -> May | D95: =TEXT(B95,"yyy") -> 2023 | F95: 45272 | G95: CUST013 | H95: PROD004 | I95: North | J95: 62 | K95: 2 | L95: 124 | M95: Credit Card | N95: Cancelled | O95: FedEx | P95: =K95*J95 -> 124 | Q95: =IF(N95="Delivered",E95-B95,"") | R95: {=_xlfn.XLOOKUP(Table1[[#This Row],[Product ID]],Table2[[#All],[Product ID]],Table2[[#All],[Category]])} -> Toys | S95: {=_xlfn.XLOOKUP(Table1[[#This Row],[Customer ID]],Table4[[#All],[Customer ID]],Table4[[#All],[Customer Name]])} -> Olivia Martinez | T95: =IF(E95-B95<=2,"Fast","Slow") -> Fast | U95: =IFERROR(IF(E95="","Cancellations",E95),0) -> Cancellations | V95: =IF(OR(F95<>"",N95="Cancelled"),"Cancelled","Delivered") -> Cancelled | W95: =IF(V95="Cancelled",1,0) -> 1 | X95: =VLOOKUP(H95,ProductMaster!$A$1:$E$23,2,0) -> Leg Set
A96: ORD0095 | B96: 45113 | C96: =TEXT(B96,"mmm") -> Jul | D96: =TEXT(B96,"yyy") -> 2023 | F96: 45266 | G96: CUST043 | H96: PROD009 | I96: South | J96: 11 | K96: 5 | L96: 55 | M96: Debit Card | N96: Cancelled | O96: Amazon Logistics | P96: =K96*J96 -> 55 | Q96: =IF(N96="Delivered",E96-B96,"") | R96: {=_xlfn.XLOOKUP(Table1[[#This Row],[Product ID]],Table2[[#All],[Product ID]],Table2[[#All],[Category]])} -> Books | S96: {=_xlfn.XLOOKUP(Table1[[#This Row],[Customer ID]],Table4[[#All],[Customer ID]],Table4[[#All],[Customer Name]])} -> Lily Reed | T96: =IF(E96-B96<=2,"Fast","Slow") -> Fast | U96: =IFERROR(IF(E96="","Cancellations",E96),0) -> Cancellations | V96: =IF(OR(F96<>"",N96="Cancelled"),"Cancelled","Delivered") -> Cancelled | W96: =IF(V96="Cancelled",1,0) -> 1 | X96: =VLOOKUP(H96,ProductMaster!$A$1:$E$23,2,0) -> Magazine
A97: ORD0096 | B97: 45176 | C97: =TEXT(B97,"mmm") -> Sep | D97: =TEXT(B97,"yyy") -> 2023 | E97: 45267 | G97: CUST017 | H97: PROD015 | I97: North | J97: 21 | K97: 2 | L97: 42 | M97: Amazon Pay | N97: Delivered | O97: UPS | P97: =K97*J97 -> 42 | Q97: =IF(N97="Delivered",E97-B97,"") -> 91 | R97: {=_xlfn.XLOOKUP(Table1[[#This Row],[Product ID]],Table2[[#All],[Product ID]],Table2[[#All],[Category]])} -> Books | S97: {=_xlfn.XLOOKUP(Table1[[#This Row],[Customer ID]],Table4[[#All],[Customer ID]],Table4[[#All],[Customer Name]])} -> Emma King | T97: =IF(E97-B97<=2,"Fast","Slow") -> Slow | U97: =IFERROR(IF(E97="","Cancellations",E97),0) -> 45267 | V97: =IF(OR(F97<>"",N97="Cancelled"),"Cancelled","Delivered") -> Delivered | W97: =IF(V97="Cancelled",1,0) -> 0 | X97: =VLOOKUP(H97,ProductMaster!$A$1:$E$23,2,0) -> Novel
A98: ORD0097 | B98: 45283 | C98: =TEXT(B98,"mmm") -> Dec | D98: =TEXT(B98,"yyy") -> 2023 | E98: 45286 | G98: CUST023 | H98: PROD018 | I98: West | J98: 95 | K98: 5 | L98: 475 | M98: Amazon Pay | N98: Delivered | O98: Amazon Logistics | P98: =K98*J98 -> 475 | Q98: =IF(N98="Delivered",E98-B98,"") -> 3 | R98: {=_xlfn.XLOOKUP(Table1[[#This Row],[Product ID]],Table2[[#All],[Product ID]],Table2[[#All],[Category]])} -> Toys | S98: {=_xlfn.XLOOKUP(Table1[[#This Row],[Customer ID]],Table4[[#All],[Customer ID]],Table4[[#All],[Customer Name]])} -> Charlotte Reed | T98: =IF(E98-B98<=2,"Fast","Slow") -> Slow | U98: =IFERROR(IF(E98="","Cancellations",E98),0) -> 45286 | V98: =IF(OR(F98<>"",N98="Cancelled"),"Cancelled","Delivered") -> Delivered | W98: =IF(V98="Cancelled",1,0) -> 0 | X98: =VLOOKUP(H98,ProductMaster!$A$1:$E$23,2,0) -> Doll House
A99: ORD0098 | B99: 45194 | C99: =TEXT(B99,"mmm") -> Sep | D99: =TEXT(B99,"yyy") -> 2023 | E99: 45199 | G99: CUST044 | H99: PROD016 | I99: South | J99: 215 | K99: 2 | L99: 430 | M99: PayPal | N99: Delivered | O99: Amazon Logistics | P99: =K99*J99 -> 430 | Q99: =IF(N99="Delivered",E99-B99,"") -> 5 | R99: {=_xlfn.XLOOKUP(Table1[[#This Row],[Product ID]],Table2[[#All],[Product ID]],Table2[[#All],[Category]])} -> Home | S99: {=_xlfn.XLOOKUP(Table1[[#This Row],[Customer ID]],Table4[[#All],[Customer ID]],Table4[[#All],[Customer Name]])} -> Grace Ward | T99: =IF(E99-B99<=2,"Fast","Slow") -> Slow | U99: =IFERROR(IF(E99="","Cancellations",E99),0) -> 45199 | V99: =IF(OR(F99<>"",N99="Cancelled"),"Cancelled","Delivered") -> Delivered | W99: =IF(V99="Cancelled",1,0) -> 0 | X99: =VLOOKUP(H99,ProductMaster!$A$1:$E$23,2,0) -> Cookware Set Pro
A100: ORD0099 | B100: 44944 | C100: =TEXT(B100,"mmm") -> Jan | D100: =TEXT(B100,"yyy") -> 2023 | F100: 44950 | G100: CUST034 | H100: PROD019 | I100: West | J100: 43 | K100: 5 | L100: 215 | M100: Credit Card | N100: Cancelled | O100: UPS | P100: =K100*J100 -> 215 | Q100: =IF(N100="Delivered",E100-B100,"") | R100: {=_xlfn.XLOOKUP(Table1[[#This Row],[Product ID]],Table2[[#All],[Product ID]],Table2[[#All],[Category]])} -> Fashion | S100: {=_xlfn.XLOOKUP(Table1[[#This Row],[Customer ID]],Table4[[#All],[Customer ID]],Table4[[#All],[Customer Name]])} -> Lily Simmons | T100: =IF(E100-B100<=2,"Fast","Slow") -> Fast | U100: =IFERROR(IF(E100="","Cancellations",E100),0) -> Cancellations | V100: =IF(OR(F100<>"",N100="Cancelled"),"Cancelled","Delivered") -> Cancelled | W100: =IF(V100="Cancelled",1,0) -> 1 | X100: =VLOOKUP(H100,ProductMaster!$A$1:$E$23,2,0) -> Formal Shirt
...

Sheet ProductMaster
A1: Product ID | B1: Product Name | C1: Category | D1: Cost Price | E1: Description
A2: PROD001 | B2: Smartphone | C2: Electronics | D2: 749 | E2: Latest model with 5G, dual SIM, and OLED display
A3: PROD002 | B3: Action Figure | C3: Toys | D3: 39 | E3: Collectible superhero action figure for ages 8+
A4: PROD003 | B4: Cookware Set | C4: Home | D4: 129 | E4: Non-stick 5-piece cookware set for daily use
A5: PROD004 | B5: Leg Set | C5: Toys | D5: 59 | E5: 300-piece creative building block toy set
A6: PROD005 | B6: T-Shirt | C6: Fashion | D6: 25 | E6: Cotton t-shirt, available in multiple colors
A7: PROD006 | B7: Shoes | C7: Fashion | D7: 89 | E7: Casual wear shoes for men and women
A8: PROD007 | B8: Puzzle | C8: Toys | D8: 29 | E8: 1000-piece jigsaw puzzle
A9: PROD008 | B9: Textbook | C9: Books | D9: 65 | E9: University-level textbook on computer science
A10: PROD009 | B10: Magazine | C10: Books | D10: 10 | E10: Monthly lifestyle magazine
A11: PROD010 | B11: Jeans | C11: Fashion | D11: 55 | E11: Slim fit denim jeans with stretch
A12: PROD011 | B12: Headphones | C12: Electronics | D12: 159 | E12: Wireless noise-cancelling over-ear headphones
A13: PROD012 | B13: Lamp | C13: Home | D13: 42 | E13: LED desk lamp with dimmable light
... A23: PROD022 | B23: Backpack | C23: Fashion | D23: 60 | E23: Waterproof backpack with laptop compartment

Sheet RegionGoals
A1: Region | B1: Sales Target
A2: Central | B2: 97500
A3: East | B3: 50500
A4: North | B4: 105000
A5: South | B5: 91500
A6: West | B6: 90750

Sheet CustomerMaster
A1: Customer ID | B1: Customer Name | C1: Customer Type | D1: City | E1: State
A2: CUST001 | B2: James Miller | C2: Business | D2: New York | E2: New York
A3: CUST002 | B3: Emily Johnson | C3: Prime | D3: Seattle | E3: Washington
A4: CUST003 | B4: Ethan Davis | C4: Prime | D4: Austin | E4: Texas
A5: CUST004 | B5: Noah Wilson | C5: Prime | D5: San Francisco | E5: California
A6: CUST005 | B6: Olivia Martinez | C6: Prime | D6: Seattle | E6: Washington
A7: CUST006 | B7: Ava Robinson | C7: Prime | D7: Chicago | E7: Illinois
A8: CUST007 | B8: Liam Walker | C8: Prime | D8: San Francisco | E8: California
A9: CUST008 | B9: Harper Young | C9: Business | D9: Dallas | E9: Texas
A10: CUST009 | B10: Jackson Allen | C10: Business | D10: Seattle | E10: Washington
A11: CUST010 | B11: Charlotte Harris | C11: Prime | D11: Chicago | E11: Illinois
A12: CUST011 | B12: Mason Hall | C12: Business | D12: Miami | E12: Florida
... A50: CUST049 | B50: Hazel Gray | C50: Business | D50: Chicago | E50: Illinois
